Workbook

Sheet MIO
B1: Title | C1: Fecha | D1: Abstract | E1: Keyword | F1: BestCategorySJR | G1: Clean_Abstract | H1: my_label | I1: my_superlabel | J1: Clean_Title
A2: 1 | B2: A methodology to compute emission projections from road transport (EmiTRANS) | C2: 2014-01-01 | D2: Atmospheric emissions from road transport have increased all around the world during the last decades more rapidly than from other pollution sources. For instance, they contribute to more than 25% of total CO, CO2, NOx, and fine particle emissions in most of the European countries. This situation shows the importance of road transport when complying with emission ceilings and air quality standards applied to these pollutants. This paper presents a modelling system to perform atmospheric emission projections (simultaneously both air quality pollutants and greenhouse gases) from road transport including the development of a tailored software tool (EmiTRANS) as a planning tool. The methodology has been developed with two purposes: 1) to obtain outputs used as inputs to the COPERT4 software to calculate emission projections and 2) to summarize outputs for policy making evaluating the effect of emission abatement measures for a vehicle fleet. This methodology has been applied to the calculation of emission projections in Spain up to 2020 under several scenarios, including a sensitivity analysis useful for a better interpretation and confidence building on the results. This case study demonstrates the EmiTRANS applicability to a country, and points out the need for combining both technical and non-technical measures (such as behavioural changes or demand management) to reduce emissions, indirectly improving air quality and contributing to mitigate climate change. (C) 2013 Elsevier Inc. All rights reserved. (general); Atmospheric emissions from road transport have increased all around the world during the last decades more rapidly than from other pollution sources. For instance, they contribute to more than 25% of total CO, CO2, NOx, and fine particle emissions in most of the European countries. This situation shows the importance of road transport when complying with emission ceilings and air quality standards applied to these pollutants. (Summary) | E2: Cancer; Emission; Emission projections; Emitrans; Estrogens; In-vitro; Inventory; Metabolites; Model; Phytoestrogens; Policies and measures; Reduction; Road transport; Sector; Sensitivity analysis; Spain; Systems; Women | F2: Management of Technology and Innovation | G2: Atmospheric emissions from road transport have increased all around the world during the last decades more rapidly than from other pollution sources. For instance, they contribute to more than 25% of total CO, CO2, NOx, and fine particle emissions in most of the European countries. This situation shows the importance of road transport when complying with emission ceilings and air quality standards applied to these pollutants. This paper presents a modelling system to perform atmospheric emission projections (simultaneously both air quality pollutants and greenhouse gases) from road transport including the development of a tailored software tool (EmiTRANS) as a planning tool. The methodology has been developed with two purposes: 1) to obtain outputs used as inputs to the COPERT4 software to calculate emission projections and 2) to summarize outputs for policy making evaluating the effect of emission abatement measures for a vehicle fleet. This methodology has been applied to the calculation of emission projections in Spain up to 2020 under several scenarios, including a sensitivity analysis useful for a better interpretation and confidence building on the results. This case study demonstrates the EmiTRANS applicability to a country, and points out the need for combining both technical and non-technical measures (such as behavioural changes or demand management) to reduce emissions, indirectly improving air quality and contributing to mitigate climate change. | H2: 13 | I2: 1 | J2: a methodology to compute emission projections from road transport emitrans
A3: 2 | B3: Matrix Product States, Random Matrix Theory and the Principle of Maximum Entropy | C3: 2013-06-01 | D3: Using random matrix techniques and the theory of Matrix Product States we show that reduced density matrices of quantum spin chains have generically maximum entropy. (general) | E3: Double-blind; Outcomes; Survival | F3: Mathematical Physics | G3: Using random matrix techniques and the theory of Matrix Product States we show that reduced density matrices of quantum spin chains have generically maximum entropy. | H3: 9 | I3: 2 | J3: matrix product states random matrix theory and the principle of maximum entropy
A4: 4 | B4: Real-time speed profile calculation for fuel saving considering unforeseen situations and travel time | C4: 2013-03-01 | D4: Driving style is a key variable which we can influence in order to reduce consumption and pollutant emissions, but other variables also need to be taken into account, such as safety, comfort and travel time. There are different alternatives for obtaining the optimal speed and gear by taking into account the vertical profile of the road and vehicle characteristics. Of these alternatives, Dynamic Programming (DP) provides fairly satisfactory results. However, this calculation involves a high computation cost when it is used to calculate long routes, which poses practical problems when the route can be varied frequently or when unexpected traffic events make it necessary to recalculate the speed profile. This study proposes a solution that is closer to the optimal solution. The algorithm is based on simple action rules for elementary road profiles that have been previously obtained using DP. Furthermore, these rules are recalculated in order to fulfil a predefined travel time. The algorithm has been used in different traffic situations on a real route and differences with the optimal solution have been evaluated so that the conditions where it works better are assessed. (general) | E4: Classification; Performance liquid-chromatography; Pigments; Profile; Quality; Skin; Varieties | F4: Mechanical Engineering | G4: Driving style is a key variable which we can influence in order to reduce consumption and pollutant emissions, but other variables also need to be taken into account, such as safety, comfort and travel time. There are different alternatives for obtaining the optimal speed and gear by taking into account the vertical profile of the road and vehicle characteristics. Of these alternatives, Dynamic Programming (DP) provides fairly satisfactory results. However, this calculation involves a high computation cost when it is used to calculate long routes, which poses practical problems when the route can be varied frequently or when unexpected traffic events make it necessary to recalculate the speed profile. This study proposes a solution that is closer to the optimal solution. The algorithm is based on simple action rules for elementary road profiles that have been previously obtained using DP. Furthermore, these rules are recalculated in order to fulfil a predefined travel time. The algorithm has been used in different traffic situations on a real route and differences with the optimal solution have been evaluated so that the conditions where it works better are assessed. | H4: 13 | I4: 1 | J4: realtime speed profile calculation for fuel saving considering unforeseen situations and travel time
A5: 5 | B5: Methodology for kinematic cycle characterization of vehicles with fixed routes in urban areas | C5: 2013-07-01 | D5: This paper analyses the driving cycles of a fleet of vehicles with predetermined urban itineraries. Most driving cycles developed for such type of vehicles do not properly address variability among itineraries. Here we develop a polygonal driving cycle that assesses each group of related routes, based on microscopic parameters. It measures the kinematic cycles of the routes traveled by the vehicle fleet, segments cycles into micro-cycles, and characterizes their properties, groups them into clusters with homogeneous kinematic characteristics within their specific micro-cycles, and constructs a standard cycle for each cluster. The process is used to study public bus operations in Madrid. (C) 2013 Elsevier Ltd. All rights reserved. (general) | E5: Depression; Driving cycle; Emissions; Patterns; Power analysis; Reliability; Traffic speed; Urban buses; Validity; Vehicles emissions | F5: Civil and Structural Engineering | G5: This paper analyses the driving cycles of a fleet of vehicles with predetermined urban itineraries. Most driving cycles developed for such type of vehicles do not properly address variability among itineraries. Here we develop a polygonal driving cycle that assesses each group of related routes, based on microscopic parameters. It measures the kinematic cycles of the routes traveled by the vehicle fleet, segments cycles into micro-cycles, and characterizes their properties, groups them into clusters with homogeneous kinematic characteristics within their specific micro-cycles, and constructs a standard cycle for each cluster. The process is used to study public bus operations in Madrid. | H5: 11 | I5: 1 | J5: methodology for kinematic cycle characterization of vehicles with fixed routes in urban areas
A6: 6 | B6: A Hierarchical Tracking Strategy for Vision-Based Applications On-Board UAVs | C6: 2013-12-01 | D6: In this paper, we apply a hierarchical tracking strategy of planar objects (or that can be assumed to be planar) that is based on direct methods for vision-based applications on-board UAVs. The use of this tracking strategy allows to achieve the tasks at real-time frame rates and to overcome problems posed by the challenging conditions of the tasks: e.g. constant vibrations, fast 3D changes, or limited capacity on-board. The vast majority of approaches make use of feature-based methods to track objects. Nonetheless, in this paper we show that although some of these feature-based solutions are faster, direct methods can be more robust under fast 3D motions (fast changes in position), some changes in appearance, constant vibrations (without requiring any specific hardware or software for video stabilization), and situations in which part of the object to track is outside of the field of view of the camera. The performance of the proposed tracking strategy on-board UAVs is evaluated with images from real-flight tests using manually-generated ground truth information, accurate position estimation using a Vicon system, and also with simulated data from a simulation environment. Results show that the hierarchical tracking strategy performs better than well-known feature-based algorithms and well-known configurations of direct methods, and that its performance is robust enough for vision-in-the-loop tasks, e.g. for vision-based landing tasks. (general) | E6: Direct methods; Hierarchical tracking; Pose estimation; Program; Software; Uavs visual tracking; Vision-based landing | F6: Artificial Intelligence | G6: In this paper, we apply a hierarchical tracking strategy of planar objects (or that can be assumed to be planar) that is based on direct methods for vision-based applications on-board UAVs. The use of this tracking strategy allows to achieve the tasks at real-time frame rates and to overcome problems posed by the challenging conditions of the tasks: e.g. constant vibrations, fast 3D changes, or limited capacity on-board. The vast majority of approaches make use of feature-based methods to track objects. Nonetheless, in this paper we show that although some of these feature-based solutions are faster, direct methods can be more robust under fast 3D motions (fast changes in position), some changes in appearance, constant vibrations (without requiring any specific hardware or software for video stabilization), and situations in which part of the object to track is outside of the field of view of the camera. The performance of the proposed tracking strategy on-board UAVs is evaluated with images from real-flight tests using manually-generated ground truth information, accurate position estimation using a Vicon system, and also with simulated data from a simulation environment. Results show that the hierarchical tracking strategy performs better than well-known feature-based algorithms and well-known configurations of direct methods, and that its performance is robust enough for vision-in-the-loop tasks, e.g. for vision-based landing tasks. | H6: 9 | I6: 2 | J6: a hierarchical tracking strategy for visionbased applications onboard uavs
A7: 7 | B7: A vision-based strategy for autonomous aerial refueling tasks | C7: 2013-08-01 | D7: Autonomous aerial refueling is a key enabling technology for both manned and unmanned aircraft where extended flight duration or range are required. The results presented within this paper offer one potential vision-based sensing solution, together with a unique test environment. A hierarchical visual tracking algorithm based on direct methods is proposed and developed for the purposes of tracking a drogue during the capture stage of autonomous aerial refueling, and of estimating its 3D position. Intended to be applied in real time to a video stream from a single monocular camera mounted on the receiver aircraft, the algorithm is shown to be highly robust, and capable of tracking large, rapid drogue motions within the frame of reference. The proposed strategy has been tested using a complex robotic testbed and with actual flight hardware consisting of a full size probe and drogue. Results show that the vision tracking algorithm can detect and track the drogue at real-time frame rates of more than thirty frames per second, obtaining a robust position estimation even with strong motions and multiple occlusions of the drogue. (C) 2013 Elsevier B.V. All rights reserved. (general) | E7: Activation; Autonomous aerial refueling; Computer vision; Direct methods; Mechanisms; Phosphatase; Probe and drogue refueling; Simulation; Unmanned aerial vehicles; Visual tracking | F7: Software | G7: Autonomous aerial refueling is a key enabling technology for both manned and unmanned aircraft where extended flight duration or range are required. The results presented within this paper offer one potential vision-based sensing solution, together with a unique test environment. A hierarchical visual tracking algorithm based on direct methods is proposed and developed for the purposes of tracking a drogue during the capture stage of autonomous aerial refueling, and of estimating its 3D position. Intended to be applied in real time to a video stream from a single monocular camera mounted on the receiver aircraft, the algorithm is shown to be highly robust, and capable of tracking large, rapid drogue motions within the frame of reference. The proposed strategy has been tested using a complex robotic testbed and with actual flight hardware consisting of a full size probe and drogue. Results show that the vision tracking algorithm can detect and track the drogue at real-time frame rates of more than thirty frames per second, obtaining a robust position estimation even with strong motions and multiple occlusions of the drogue. | H7: 9 | I7: 2 | J7: a visionbased strategy for autonomous aerial refueling tasks
A8: 8 | B8: Analysis of the operator action and the single failure criteria in a SGTR sequence using best estimate assumptions with TRACE 5.0 | C8: 2013-04-17 | D8: Steam Generator Tube Rupture (SGTR) sequences in Pressurized Water Reactors are known to be one of the most demanding transients for the operating crew. SGTR are a special kind of transient as they could lead to radiological releases without core damage or containment failure, as they can constitute a direct path from the reactor coolant system to the environment. The first methodology used to perform the Deterministic Safety Analysis (DSA) of a SGTR did not credit the operator action for the first 30 min of the transient, assuming that the operating crew was able to stop the primary to secondary leakage within that period of time. However, the different real SGTR accident cases happened in the USA and over the world demonstrated that the operators usually take more than 30 min to stop the leakage in actual sequences. Some methodologies were raised to overcome that fact, considering operator actions from the beginning of the transient, as it is done in Probabilistic Safety Analysis. This paper presents the results of comparing different assumptions regarding the single failure criteria and the operator action taken from the most common methodologies included in the different Deterministic Safety Analysis. One single failure criteria that has not been analysed previously in the literature is proposed and analysed in this paper too. The comparison is done with a PWR Westinghouse three loop model in TRACE code (Almaraz NPP) with best estimate assumptions but including deterministic hypothesis such as single failure criteria or loss of offsite power. The behaviour of the reactor is quite diverse depending on the different assumptions made regarding the operator actions. On the other hand, although there are high conservatisms included in the hypothesis, as the single failure criteria, all the results are quite far from the regulatory limits. In addition, some improvements to the Emergency Operating Procedures to minimize the offsite release from the damaged SG in case of a SGTR are outlined taking into account the offsite dose sensitivity results. (C) 2013 Elsevier Ltd. All rights reserved. (general) | E8: Fsar; Mto; Offsite dose; Radtrad; Sgtr; Trace; Trial; Visceral leishmaniasis | F8: Nuclear Energy and Engineering | G8: Steam Generator Tube Rupture (SGTR) sequences in Pressurized Water Reactors are known to be one of the most demanding transients for the operating crew. SGTR are a special kind of transient as they could lead to radiological releases without core damage or containment failure, as they can constitute a direct path from the reactor coolant system to the environment. The first methodology used to perform the Deterministic Safety Analysis (DSA) of a SGTR did not credit the operator action for the first 30 min of the transient, assuming that the operating crew was able to stop the primary to secondary leakage within that period of time. However, the different real SGTR accident cases happened in the USA and over the world demonstrated that the operators usually take more than 30 min to stop the leakage in actual sequences. Some methodologies were raised to overcome that fact, considering operator actions from the beginning of the transient, as it is done in Probabilistic Safety Analysis. This paper presents the results of comparing different assumptions regarding the single failure criteria and the operator action taken from the most common methodologies included in the different Deterministic Safety Analysis. One single failure criteria that has not been analysed previously in the literature is proposed and analysed in this paper too. The comparison is done with a PWR Westinghouse three loop model in TRACE code (Almaraz NPP) with best estimate assumptions but including deterministic hypothesis such as single failure criteria or loss of offsite power. The behaviour of the reactor is quite diverse depending on the different assumptions made regarding the operator actions. On the other hand, although there are high conservatisms included in the hypothesis, as the single failure criteria, all the results are quite far from the regulatory limits. In addition, some improvements to the Emergency Operating Procedures to minimize the offsite release from the damaged SG in case of a SGTR are outlined taking into account the offsite dose sensitivity results. | H8: 7 | I8: 2 | J8: analysis of the operator action and the single failure criteria in a sgtr sequence using best estimate assumptions with trace 50
A9: 10 | B9: Fungal biodeterioration of color cinematographic films of the cultural heritage of Cuba | C9: 2013-10-01 | D9: Until recently, cinematographic film was largely cellulose-triacetate-based. However, this material is highly susceptible to biodeterioration, thus placing historic film collections, an important part of the cultural heritage of many countries, at risk. In the present study, samples taken from several biodeteriorated color cinematographic films belonging to the collection of the Cuban Institute for Cinematographic Industry and Arts (ICAIC) were investigated. Infrared spectroscopy showed that all films were of the same composition, i.e., a gelatin emulsion coating one side of a cellulose-triacetate-based film support. The films were analyzed by environmental scanning electron microscopy and scanning electron microscopy to determine the degree of biodeterioration and the type of colonizing microorganisms. Significant fungal colonization was found on both sides of the films in all samples, with a higher concentration of fungi on the gelatin emulsion side. Epifluorescence microscopy of fluorochrome-dyed films demonstrated that some of the fungi were still active, indicating that the films under study, and probably others at the ICAIC, are at risk of further deterioration. Fungi were identified by molecular biology techniques. The fungi mainly responsible for the observed biodeterioration were those belonging to the genera Aspergillus and Cladosporium, although other genera, such as Microascus and Penicillium, were identified as well. In accordance with the findings described herein, the existing guidelines for the prevention and control of film biodeterioration are discussed. (c) 2012 Elsevier Ltd. All rights reserved. (general) | E9: Archive; Biodegradation; Biodeterioration; Cinematographic film; Comparative efficacy; Cultural heritage; Degradation; Double-blind; Fungi; Microascus; Parameters; Sequence alignment | F9: Waste Management and Disposal | G9: Until recently, cinematographic film was largely cellulose-triacetate-based. However, this material is highly susceptible to biodeterioration, thus placing historic film collections, an important part of the cultural heritage of many countries, at risk. In the present study, samples taken from several biodeteriorated color cinematographic films belonging to the collection of the Cuban Institute for Cinematographic Industry and Arts (ICAIC) were investigated. Infrared spectroscopy showed that all films were of the same composition, i.e., a gelatin emulsion coating one side of a cellulose-triacetate-based film support. The films were analyzed by environmental scanning electron microscopy and scanning electron microscopy to determine the degree of biodeterioration and the type of colonizing microorganisms. Significant fungal colonization was found on both sides of the films in all samples, with a higher concentration of fungi on the gelatin emulsion side. Epifluorescence microscopy of fluorochrome-dyed films demonstrated that some of the fungi were still active, indicating that the films under study, and probably others at the ICAIC, are at risk of further deterioration. Fungi were identified by molecular biology techniques. The fungi mainly responsible for the observed biodeterioration were those belonging to the genera Aspergillus and Cladosporium, although other genera, such as Microascus and Penicillium, were identified as well. In accordance with the findings described herein, the existing guidelines for the prevention and control of film biodeterioration are discussed. (c) 2012 Elsevier Ltd. All rights reserved. | H9: 9 | I9: 2 | J9: fungal biodeterioration of color cinematographic films of the cultural heritage of cuba
A10: 11 | B10: Direct and Inverse Results on Row Sequences of Hermite-Pad, Approximants | C10: 2013-08-01 | D10: We give necessary and sufficient conditions for the convergence with geometric rate of the common denominators of simultaneous rational interpolants with a bounded number of poles. The conditions are expressed in terms of intrinsic properties of the system of functions used to build the approximants. Exact rates of convergence for these denominators and the simultaneous rational approximants are provided. (general) | E10: Convergence; Defects; Dogs; Hermite-pade approximation; Inverse results; Montessus de ballore theorem; Proliferation; Rate of convergence; Repair; Simultaneous approximation | F10: Computational Mathematics | G10: We give necessary and sufficient conditions for the convergence with geometric rate of the common denominators of simultaneous rational interpolants with a bounded number of poles. The conditions are expressed in terms of intrinsic properties of the system of functions used to build the approximants. Exact rates of convergence for these denominators and the simultaneous rational approximants are provided. | H10: 9 | I10: 2 | J10: direct and inverse results on row sequences of hermitepad approximants
A11: 12 | B11: Tactile-Sight: A Sensory Substitution Device Based on Distance-Related Vibrotactile Flow Regular Paper | C11: 2013-06-17 | D11: Sensory substitution is a research field of increasing interest with regard to technical, applied and theoretical issues. Among the latter, it is of central interest to understand the form in which humans perceive the environment. Ecological psychology, among other approaches, proposes that we can detect higher-order informational variables (in the sense that they are defined over substantial spatial and temporal intervals) that specify our interaction with the environment. When using a vibrotactile sensory substitution device, it is reasonable to ask if stimulation on the skin may be exploitable to detect higher-order variables. Motivated by this question, a portable vibrotactile sensory substitution device was built, using distance-based information as a source and driving a large number of vibrotactile actuators (72 in the reported version, 120 max). The portable device was designed to explore real environments, allowing natural unrestricted movement for the user while providing contingent real-time vibrotactile information. Two preliminary experiments were performed. In the first one, participants were asked to detect the time to contact of an approaching ball in a simulated (desktop) environment. Reasonable performance was observed in all experimental conditions, including the one with only tactile stimulation. In the second experiment, a portable version of the device was used in a real environment, where participants were asked to hit an approaching ball. Participants were able to coordinate their arm movements with vibrotactile stimulation in appropriate timing. We conclude that vibrotactile flow can be generated by distance-based activation of the actuators and that this stimulation on the skin allows users to perceive time-to-contact related environmental properties. (general) | E11: Hadron colliders; Movement; Phenomenology; Sensory substitution; Time to contact; Vibrotactile flow | F11: Artificial Intelligence | G11: Sensory substitution is a research field of increasing interest with regard to technical, applied and theoretical issues. Among the latter, it is of central interest to understand the form in which humans perceive the environment. Ecological psychology, among other approaches, proposes that we can detect higher-order informational variables (in the sense that they are defined over substantial spatial and temporal intervals) that specify our interaction with the environment. When using a vibrotactile sensory substitution device, it is reasonable to ask if stimulation on the skin may be exploitable to detect higher-order variables. Motivated by this question, a portable vibrotactile sensory substitution device was built, using distance-based information as a source and driving a large number of vibrotactile actuators (72 in the reported version, 120 max). The portable device was designed to explore real environments, allowing natural unrestricted movement for the user while providing contingent real-time vibrotactile information. Two preliminary experiments were performed. In the first one, participants were asked to detect the time to contact of an approaching ball in a simulated (desktop) environment. Reasonable performance was observed in all experimental conditions, including the one with only tactile stimulation. In the second experiment, a portable version of the device was used in a real environment, where participants were asked to hit an approaching ball. Participants were able to coordinate their arm movements with vibrotactile stimulation in appropriate timing. We conclude that vibrotactile flow can be generated by distance-based activation of the actuators and that this stimulation on the skin allows users to perceive time-to-contact related environmental properties. | H11: 3 | I11: 1 | J11: tactilesight a sensory substitution device based on distancerelated vibrotactile flow regular paper
A12: 13 | B12: Improved variability classification of CoRoT targets with Giraffe spectra | C12: 2013-11-20 | D12: Aims. We present an improved method for automated stellar variability classification, using fundamental parameters derived from high resolution spectra, with the goal to improve the variability classification obtained using information derived from CoRoT light curves only. Although we focus on Giraffe spectra and CoRoT light curves in this work, the methods are much more widely applicable. Methods. In order to improve the variability classification obtained from the photometric time series, only rough estimates of the stellar physical parameters (T-eff and log (g)) are needed because most variability types that overlap in the space of time series parameters, are well separated in the space of physical parameters (e. g. gamma Dor/SPB or delta Sct/beta Cep). In this work, several state-of-the-art machine learning techniques are combined to estimate these fundamental parameters from high resolution Giraffe spectra. Next, these parameters are used in a multi-stage Gaussian-Mixture classifier to perform an improved supervised variability classification of CoRoT light curves. The variability classifier can be used independently of the regression module that estimates the physical parameters, so that non-spectroscopic estimates derived e. g. from photometric colour indices can be used instead. Results. T-eff and log (g) are derived from Giraffe spectra, for 6832 CoRoT targets. The use of those parameters in addition to information extracted from the CoRoT light curves, significantly improves the results of our previous automated stellar variability classification. Several new pulsating stars are identified with high confidence levels, including hot pulsators such as SPB and beta Cep, and several gamma Dor-delta Sct hybrids. From our samples of new gamma Dor and delta Sct stars, we find strong indications that the instability domains for both types of pulsators are larger than previously thought. (general) | E12: Methods: data analysis; Methods: statistical; Neural-networks; Resolution; Stars: fundamental parameters; Stars: oscillations; Stars: variables: general; System; Techniques: spectroscopic | F12: Astronomy and Astrophysics | G12: Aims. We present an improved method for automated stellar variability classification, using fundamental parameters derived from high resolution spectra, with the goal to improve the variability classification obtained using information derived from CoRoT light curves only. Although we focus on Giraffe spectra and CoRoT light curves in this work, the methods are much more widely applicable. Methods. In order to improve the variability classification obtained from the photometric time series, only rough estimates of the stellar physical parameters (T-eff and log (g)) are needed because most variability types that overlap in the space of time series parameters, are well separated in the space of physical parameters (e. g. gamma Dor/SPB or delta Sct/beta Cep). In this work, several state-of-the-art machine learning techniques are combined to estimate these fundamental parameters from high resolution Giraffe spectra. Next, these parameters are used in a multi-stage Gaussian-Mixture classifier to perform an improved supervised variability classification of CoRoT light curves. The variability classifier can be used independently of the regression module that estimates the physical parameters, so that non-spectroscopic estimates derived e. g. from photometric colour indices can be used instead. Results. T-eff and log (g) are derived from Giraffe spectra, for 6832 CoRoT targets. The use of those parameters in addition to information extracted from the CoRoT light curves, significantly improves the results of our previous automated stellar variability classification. Several new pulsating stars are identified with high confidence levels, including hot pulsators such as SPB and beta Cep, and several gamma Dor-delta Sct hybrids. From our samples of new gamma Dor and delta Sct stars, we find strong indications that the instability domains for both types of pulsators are larger than previously thought. | H12: 9 | I12: 2 | J12: improved variability classification of corot targets with giraffe spectra
A13: 14 | B13: Transformer-Coupled Converter for Voltage Modulation Techniques | C13: 2013-01-01 | D13: In high performance digital systems as well as in RF systems, voltage scaling and modulation techniques have been adopted to achieve a more efficient processing of the energy. The implementation of such techniques relies on a power supply that is capable of rapidly adjusting the system supply voltage. In this paper, a pulsewidth modulation multiphase topology with magnetic coupling is proposed for its use in voltage modulation techniques. Since the magnetic coupling in this topology is done with transformers instead of coupled inductors, the energy storage is reduced and very fast voltage changes are achieved. Advantages and drawbacks of this topology have been previously presented in the literature and in this paper, the design criteria for implementing a power supply for the envelope elimination and restoration technique in an RF system are presented along with an implementation of the power supply. (general) | E13: Envelope elimination and restoration (eer) technique; In-vitro; Inductance; Modulation; Multiphase coupled converter; No energy storage; Optimization; Power; Power supplies; Radio frequency; Regulators; Rf power amplifier; Ruminal fermentation; Topology; Voltage control; Voltage modulation | F13: Electrical and Electronic Engineering | G13: In high performance digital systems as well as in RF systems, voltage scaling and modulation techniques have been adopted to achieve a more efficient processing of the energy. The implementation of such techniques relies on a power supply that is capable of rapidly adjusting the system supply voltage. In this paper, a pulsewidth modulation multiphase topology with magnetic coupling is proposed for its use in voltage modulation techniques. Since the magnetic coupling in this topology is done with transformers instead of coupled inductors, the energy storage is reduced and very fast voltage changes are achieved. Advantages and drawbacks of this topology have been previously presented in the literature and in this paper, the design criteria for implementing a power supply for the envelope elimination and restoration technique in an RF system are presented along with an implementation of the power supply. | H13: 9 | I13: 2 | J13: transformercoupled converter for voltage modulation techniques
... A48: 52 | B48: Antigen-Antibody Affinity for Dry Eye Biomarkers by Label Free Biosensing | C48: 2015-08-13 | D48: The specificity and affinity of antibody-antigen interactions is a fundamental way to achieve reliable biosensing responses. Different proteins involved with dry eye dysfunction: ANXA1, ANXA11, CST4, PRDX5, PLAA and S100A6; were validated as biomarkers. In this work several antibodies were tested for ANXA1, ANXA11 and PRDX5 to select the best candidates for each biomarker. The results were obtained by using Biophotonic Sensing Cells (BICELLs) as an efficient methodology for label-free biosensing and compared with the Enzyme-Linked Immuno Sorbent Assay (ELISA) technique. (Summary); Univ Politecn Madrid, Ctr Biomed Technol, Opt Photon & Biophoton Lab, Campus Montegancedo, Madrid 28223, Spain. mariafe.laguna@upm.es; m.holgado@upm.es; ana.lopez@upm.es; beatriz.santamaria@ctb.upm.es; alavin@etsii.upm.es; javier.soria@bioftalmik.com; tatiana.suarez@bioftalmik.com; carlota.bardina@antibodybcn.com; monica.jara@antibodybcn.com; fj.sanza@upm.es; rafael.casquel@upm.es (Author of contact); This work has been supported under the Project INNBIOD (REF: IPT-2011-1429-010000) under the Spanish Ministry of Economy and Competitiveness (INNPACT program), the Project PLATON (REF: TEC2012-31145) under the Spanish Ministry of Economy and competitiveness (Plan Nacional 2012 Investigacion fundamental no orientada) and ENVIGUARD EUROPEAN PROJECT FP7-OCEAN-2013. We acknowledge specially Bioftalmik and Antibody Bcn for theirtechnical and scientific support, as well as for the bio-chemical reagents to carry out the experiments described in this article. (Recognitions linked to item); Laguna M., Universidad Politécnica de Madrid; Holgado M., Universidad Politécnica de Madrid; Hernandez A., Universidad Politécnica de Madrid; Santamaría B., Universidad Politécnica de Madrid; Lavín A., Universidad Politécnica de Madrid; Soria J., Bioftalmik. Parque Tecnológico Zamudio Ed. 800 2ª Planta; Suarez T., Bioftalmik. Parque Tecnológico Zamudio Ed. 800 2ª Planta; Bardina C., AntibodyBcn; Jara M., AntibodyBcn; Sanza F., Universidad Politécnica de Madrid; Casquel R., Universidad Politécnica de Madrid (Authors with Filk) | E48: Biosensors; Dry eye biomarkers; Label-free immunoassay; Photonic sensing cells bicells; Su-8 | F48: Electrical and Electronic Engineering | G48: The specificity and affinity of antibody-antigen interactions is a fundamental way to achieve reliable biosensing responses. Different proteins involved with dry eye dysfunction: ANXA1, ANXA11, CST4, PRDX5, PLAA and S100A6; were validated as biomarkers. In this work several antibodies were tested for ANXA1, ANXA11 and PRDX5 to select the best candidates for each biomarker. The results were obtained by using Biophotonic Sensing Cells (BICELLs) as an efficient methodology for label-free biosensing and compared with the Enzyme-Linked Immuno Sorbent Assay (ELISA) technique. | H48: 3 | I48: 1 | J48: antigenantibody affinity for dry eye biomarkers by label free biosensing
A49: 53 | B49: A New Putative Caulimoviridae Genus Discovered through Air Metagenomics | C49: 2018-10-11 | D49: Members of the Caulimoviridae family are important plant pathogens. These circular double-stranded DNA viruses may integrate into the host genome, although this integration is not required for the viral replication cycle. Here, we describe three complete genomes belonging to a new putative Caulimoviridae genus discovered through air metagenomics. (Summary) | F49: Genetics | G49: Members of the Caulimoviridae family are important plant pathogens. These circular double-stranded DNA viruses may integrate into the host genome, although this integration is not required for the viral replication cycle. Here, we describe three complete genomes belonging to a new putative Caulimoviridae genus discovered through air metagenomics. | H49: 13 | I49: 1 | J49: a new putative caulimoviridae genus discovered through air metagenomics
A50: 54 | B50: Research on the methods for the mass production of multi-scale organs-on-chips | C50: 2018-11-07 | D50: © 2018 by the authors. The success of labs- and organs-on-chips as transformative technologies in the biomedical arena relies on our capacity of solving some current challenges related to their design, modeling, manufacturability, and usability. Among present needs for the industrial scalability and impact promotion of these bio-devices, their sustainable mass production constitutes a breakthrough for reaching the desired level of repeatability in systematic testing procedures based on labs- and organs-on-chips. The use of adequate biomaterials for cell-culture processes and the achievement of the multi-scale features required, for in vitro modeling the physiological interactions among cells, tissues, and organoids, which prove to be demanding requirements in terms of production. This study presents an innovative synergistic combination of technologies, including: laser stereolithography, laser material processing on micro-scale, electroforming, and micro-injection molding, which enables the rapid creation of multi-scale mold cavities for the industrial production of labs- and organs-on-chips using thermoplastics apt for in vitro testing. The procedure is validated by the design, rapid prototyping, mass production, and preliminary testing with human mesenchymal stem cells of a conceptual multi-organ-on-chip platform, which is conceived for future studies linked to modeling cell-to-cell communication, understanding cell-material interactions, and studying metastatic processes. (Summary); Lantada A., Universidad Politécnica de Madrid; Pfleging W., Karlsruhe Institute of Technology, Campus North , Karlsruhe Nano Micro Facility; Besser H., Karlsruhe Institute of Technology, Campus North , Karlsruhe Nano Micro Facility; Guttmann M., Karlsruhe Institute of Technology, Campus North , Karlsruhe Nano Micro Facility; Wissmann M., Karlsruhe Institute of Technology, Campus North , Karlsruhe Nano Micro Facility; Plewa K., Karlsruhe Institute of Technology, Campus North , Karlsruhe Nano Micro Facility; Smyrek P., Karlsruhe Institute of Technology, Campus North , Karlsruhe Nano Micro Facility; Piotter V., Karlsruhe Institute of Technology, Campus North , Karlsruhe Nano Micro Facility; García-Ruíz J., Universidad Autónoma de Madrid (Authors with Filk) | E50: additive manufacturing; biomedical microdevices; electroforming; labs-on-chips; laser materials processing; mass production; micro-injection molding; mold fabrication; Additive manufacturing; Biomedical microdevices; Electroforming; Labs-on-chips; Laser materials processing; Mass production; Micro-injection molding; Mold fabrication; Organs-on-chips | F50: Polymers and Plastics | G50: The success of labs- and organs-on-chips as transformative technologies in the biomedical arena relies on our capacity of solving some current challenges related to their design, modeling, manufacturability, and usability. Among present needs for the industrial scalability and impact promotion of these bio-devices, their sustainable mass production constitutes a breakthrough for reaching the desired level of repeatability in systematic testing procedures based on labs- and organs-on-chips. The use of adequate biomaterials for cell-culture processes and the achievement of the multi-scale features required, for in vitro modeling the physiological interactions among cells, tissues, and organoids, which prove to be demanding requirements in terms of production. This study presents an innovative synergistic combination of technologies, including: laser stereolithography, laser material processing on micro-scale, electroforming, and micro-injection molding, which enables the rapid creation of multi-scale mold cavities for the industrial production of labs- and organs-on-chips using thermoplastics apt for in vitro testing. The procedure is validated by the design, rapid prototyping, mass production, and preliminary testing with human mesenchymal stem cells of a conceptual multi-organ-on-chip platform, which is conceived for future studies linked to modeling cell-to-cell communication, understanding cell-material interactions, and studying metastatic processes. | H50: 3 | I50: 1 | J50: research on the methods for the mass production of multiscale organsonchips
A51: 55 | B51: Assessment of full-scale tertiary wastewater treatment by UV-C based-AOPs: Removal or persistence of antibiotics and antibiotic resistance genes? | C51: 2019-02-20 | D51: © 2018 Elsevier B.V. This research reports for the first time the full-scale application of different homogeneous Advanced Oxidation Processes (AOPs) (H 2 O 2 /UV-C, PMS/UV-C and PMS/Fe(II)/UV-C) for the removal of antibiotics (ABs) and antibiotic resistance genes (ARGs) from wastewater effluent at Estiviel wastewater treatment plant (WWTP) (Toledo, Spain). AOPs based on the photolytic decomposition of H 2 O 2 and peroxymonosulfate tested at low dosages (0.05–0.5 mM) and with very low UV-C contact time (4–18 s) demonstrated to be more efficient than UV-C radiation alone on the removal of the analyzed ABs. PMS (0.5 mM) combined with UV-C (7 s contact time) was the most efficient treatment in terms of AB removal: 7 out of 10 ABs detected in the wastewater were removed more efficiently than using the other oxidants. In terms of ARGs removal efficiency, UV-C alone seemed the most efficient treatment, although H 2 O 2 /UV-C, PMS/UV-C and PMS/Fe(II)/UV-C were supposed to generate higher concentrations of free radicals. The results show that treatments with the highest removal of ABs and ARGs did not coincide, which could be attributed to the competition between DNA and oxidants in the absorption of UV photons, reducing the direct photolysis of the DNA. Whereas the photolytic ABs removal is improved by the generation of hydroxyl and sulfate radicals, the opposite behavior occurs in the case of ARGs. These results suggest that a compromise between ABs and ARGs removal must be achieved in order to optimize wastewater treatment processes. (Summary); Rodríguez-Chueca J., Universidad Rey Juan Carlos , Universidad Politécnica de Madrid; Varella della Giustina S., Universitat de Girona; Rocha J., Universidade Catolica Portuguesa, Porto; Fernandes T., Universidade Catolica Portuguesa, Porto; Pablos C., Universidad Rey Juan Carlos; Encinas Á., FCC Aqualia, S.A.; Barceló D., Universitat de Girona , CSIC - Instituto de Diagnostico Ambiental y Estudios del Agua (IDAEA); Rodríguez-Mozaz S., Universitat de Girona; Manaia C., Universidade Catolica Portuguesa, Porto; Marugán J., Universidad Rey Juan Carlos (Authors with Filk) | E51: Activated persulfate; Advanced oxidation; Antibiotics; Aqueous-solutions; Degradation; Disinfection; Escherichia-coli; Full-scale; Hydroxyl radicals; Kinetics; Peroxymonosulfate; Resistance genes; Sulfate; Sulfate radicals; Uv-c radiation; Wwtp | F51: Environmental Engineering | G51: V. This research reports for the first time the full-scale application of different homogeneous Advanced Oxidation Processes (AOPs) (H 2 O 2 /UV-C, PMS/UV-C and PMS/Fe(II)/UV-C) for the removal of antibiotics (ABs) and antibiotic resistance genes (ARGs) from wastewater effluent at Estiviel wastewater treatment plant (WWTP) (Toledo, Spain). AOPs based on the photolytic decomposition of H 2 O 2 and peroxymonosulfate tested at low dosages (0.05–0.5 mM) and with very low UV-C contact time (4–18 s) demonstrated to be more efficient than UV-C radiation alone on the removal of the analyzed ABs. PMS (0.5 mM) combined with UV-C (7 s contact time) was the most efficient treatment in terms of AB removal: 7 out of 10 ABs detected in the wastewater were removed more efficiently than using the other oxidants. In terms of ARGs removal efficiency, UV-C alone seemed the most efficient treatment, although H 2 O 2 /UV-C, PMS/UV-C and PMS/Fe(II)/UV-C were supposed to generate higher concentrations of free radicals. The results show that treatments with the highest removal of ABs and ARGs did not coincide, which could be attributed to the competition between DNA and oxidants in the absorption of UV photons, reducing the direct photolysis of the DNA. Whereas the photolytic ABs removal is improved by the generation of hydroxyl and sulfate radicals, the opposite behavior occurs in the case of ARGs. These results suggest that a compromise between ABs and ARGs removal must be achieved in order to optimize wastewater treatment processes. | H51: 6 | I51: 1 | J51: assessment of fullscale tertiary wastewater treatment by uvc basedaops removal or persistence of antibiotics and antibiotic resistance genes
A52: 56 | B52: Evaluation of photoassisted treatments for norfloxacin removal in water using mesoporous Fe 2 O 3 -TiO 2 materials | C52: 2019-05-15 | D52: © 2019 Elsevier Ltd We report the synthesis of mesoporous TiO 2 and mesoporous Fe 2 O 3 -TiO 2 catalysts by using a structure-directing-surfactant method, their characterization and their employment as photocatalysts for norfloxacin degradation in aqueous solution. The main findings show that in the presence of both O 2 and H 2 O 2 , Fe-containing mesoporous titania (Fe 2 O 3 -TiO 2 ), with iron percentages between 1 and 3 wt%, exhibited norfloxacin degradation rates more than 60% greater than otherwise identical mesoporous titania without iron. Furthermore, the activity of the mesoporous composite catalysts also exceeds that of titania when illuminated with 405 nm light-emitting diodes. Iron loading improved the photocatalytic activity for norfloxacin degradation with values of apparent reaction rate constants of 0.037 min −1 and 0.076 min −1 with 1 and 3 surface wt.% of iron, respectively. An optimum of activity was found with the 3 wt% Fe 2 O 3 -TiO 2 catalyst. Under these conditions, 10 mg/L of norfloxacin is reacted essentially to completion and 90% of total organic carbon conversion was obtained within 120 min of reaction. This higher organic carbon conversion degree was reached due to the photo-oxidation of short-chain organic acids. The high activity of the as-synthesized mesoporous composites is attributed to the additional iron phase which led to the different reactions for H 2 O 2 decomposition, but also due to the improvement in light absorbance. Finally, the activity of the most active catalyst was found to be stable over multiple sequential runs, which was related to a negligible amount of iron leaching (<0.1%) from these materials. (Summary); García-Muñoz P., Universidad Autónoma de Madrid , University of California, Santa Barbara; Zussblatt N., University of California, Santa Barbara; Pliego G., Universidad Autónoma de Madrid; Zazo J., Universidad Autónoma de Madrid; Fresno F., IMDEA Energy Institute; Chmelka B., University of California, Santa Barbara; Casas J., Universidad Autónoma de Madrid (Authors with Filk) | E52: antibiotic; hydrogen peroxide; mesoporous catalysts; mineralization; Antibiotic; Hydrogen peroxide; Mesoporous catalysts; Mineralization; Photocatalysis | F52: Environmental Engineering | G52: The main findings show that in the presence of both O 2 and H 2 O 2 , Fe-containing mesoporous titania (Fe 2 O 3 -TiO 2 ), with iron percentages between 1 and 3 wt%, exhibited norfloxacin degradation rates more than 60% greater than otherwise identical mesoporous titania without iron. Furthermore, the activity of the mesoporous composite catalysts also exceeds that of titania when illuminated with 405 nm light-emitting diodes. Iron loading improved the photocatalytic activity for norfloxacin degradation with values of apparent reaction rate constants of 0.037 min −1 and 0.076 min −1 with 1 and 3 surface wt.% of iron, respectively. An optimum of activity was found with the 3 wt% Fe 2 O 3 -TiO 2 catalyst. Under these conditions, 10 mg/L of norfloxacin is reacted essentially to completion and 90% of total organic carbon conversion was obtained within 120 min of reaction. This higher organic carbon conversion degree was reached due to the photo-oxidation of short-chain organic acids. The high activity of the as-synthesized mesoporous composites is attributed to the additional iron phase which led to the different reactions for H 2 O 2 decomposition, but also due to the improvement in light absorbance. Finally, the activity of the most active catalyst was found to be stable over multiple sequential runs, which was related to a negligible amount of iron leaching (<0.1%) from these materials. | H52: 6 | I52: 1 | J52: evaluation of photoassisted treatments for norfloxacin removal in water using mesoporous fe 2 o 3 tio 2 materials
A53: 57 | B53: Impedance-based stability and transient-performance assessment applying maximum peak criteria | C53: 2013-01-01 | D53: The impedance-based stability-assessment method has turned out to be a very effective tool and its usage is rapidly growing in different applications ranging from the conventional interconnected dc/dc systems to the grid-connected renewable energy systems. The results are sometime given as a certain forbidden region in the complex plane out of which the impedance ratio - known as minor-loop gain - shall stay for ensuring robust stability. This letter discusses the circle-like forbidden region occupying minimum area in the complex plane, defined by applying maximum peak criteria, which is well-known theory in control engineering. The investigation shows that the circle-like forbidden region will ensure robust stability only if the impedance-based minor-loop gain is determined at the very input or output of each subsystem within the interconnected system. Experimental evidence is provided based on a small-scale dc/dc distributed system. © 1986-2012 IEEE. (Summary); Vesti S., Universidad Politécnica de Madrid; Suntio T., Tampere University of Technology; Oliver J., Universidad Politécnica de Madrid; Prieto R., Universidad Politécnica de Madrid; Cobos J., Universidad Politécnica de Madrid (Authors with Filk) | E53: Minor-loop gain; Sensitivity function; Stability; Switched-mode converter; Transient performance | F53: Electrical and Electronic Engineering | G53: The impedance-based stability-assessment method has turned out to be a very effective tool and its usage is rapidly growing in different applications ranging from the conventional interconnected dc/dc systems to the grid-connected renewable energy systems. The results are sometime given as a certain forbidden region in the complex plane out of which the impedance ratio - known as minor-loop gain - shall stay for ensuring robust stability. This letter discusses the circle-like forbidden region occupying minimum area in the complex plane, defined by applying maximum peak criteria, which is well-known theory in control engineering. The investigation shows that the circle-like forbidden region will ensure robust stability only if the impedance-based minor-loop gain is determined at the very input or output of each subsystem within the interconnected system. Experimental evidence is provided based on a small-scale dc/dc distributed system. | H53: 9 | I53: 2 | J53: impedancebased stability and transientperformance assessment applying maximum peak criteria
A54: 58 | B54: Effect of control method on impedance-based interactions in a buck converter | C54: 2013-05-23 | D54: All the interconnected regulated systems are prone to impedance-based interactions making them sensitive to instability and transient-performance degradation. The applied control method affects significantly the characteristics of the converter in terms of sensitivity to different impedance interactions. This paper provides for the first time the whole set of impedance-type internal parameters and the formulas according to which the interaction sensitivity can be fully explained and analyzed. The formulation given in this paper can be utilized equally either based on measured frequency responses or on predicted analytic transfer functions. Usually, the distributed dc-dc systems are constructed by using ready-made power modules without having thorough knowledge on the actual power-stage and control-system designs. As a consequence, the interaction characterization has to be based on the frequency responses measureable via the input and output terminals. A buck converter with four different control methods is experimentally characterized in frequency domain to demonstrate the effect of control method on the interaction sensitivity. The presented analytical models are used to explain the phenomena behind the changes in the interaction sensitivity. © 1986-2012 IEEE. (Summary); Vesti S., Universidad Politécnica de Madrid; Suntio T., Tampere University of Technology; Oliver J., Universidad Politécnica de Madrid; Prieto R., Universidad Politécnica de Madrid; Cobos J., Universidad Politécnica de Madrid (Authors with Filk) | E54: Analytical models; Buck converter; Dynamic behavior; Feedforward neural networks; Frequency measurement; Impedance; Minor-loop gain; Sensitivity; Source/load interactions; Stability; Stability analysis; Transfer functions | F54: Electrical and Electronic Engineering | G54: All the interconnected regulated systems are prone to impedance-based interactions making them sensitive to instability and transient-performance degradation. The applied control method affects significantly the characteristics of the converter in terms of sensitivity to different impedance interactions. This paper provides for the first time the whole set of impedance-type internal parameters and the formulas according to which the interaction sensitivity can be fully explained and analyzed. The formulation given in this paper can be utilized equally either based on measured frequency responses or on predicted analytic transfer functions. Usually, the distributed dc-dc systems are constructed by using ready-made power modules without having thorough knowledge on the actual power-stage and control-system designs. As a consequence, the interaction characterization has to be based on the frequency responses measureable via the input and output terminals. A buck converter with four different control methods is experimentally characterized in frequency domain to demonstrate the effect of control method on the interaction sensitivity. The presented analytical models are used to explain the phenomena behind the changes in the interaction sensitivity. | H54: 9 | I54: 2 | J54: effect of control method on impedancebased interactions in a buck converter
A55: 59 | B55: Modeling electronic power converters in smart dc microgrids - An overview | C55: 2018-11-01 | D55: © 2010-2012 IEEE. Electronic power converters (EPCs) are the key elements of the smart dc microgrid architectures. In order to enhance the controllability of the system, most of the elements are envisioned to be connected to the different buses through EPCs. Therefore, power flow, stability, and dynamic response in the microgrid are function of the behavior of the EPCs and their control loops. Besides, dc microgrids constitute a new paradigm in power distribution systems due to the high variability of their operating conditions, owing to the intermittent behavior of the renewable sources and customer energy consumption. Furthermore, in order to deal with this variability, the power converters can modify their operation mode, adding complexity to the dynamic and stability analysis of the system. This paper gives an overview of the various analytical and blackbox modeling strategies applied to smart dc micro/nanogrids. Different linear and nonlinear modeling techniques are reviewed describing their capabilities, but also their limitations. Finally, differences among blackbox models will be highlighted by means of illustrative examples. (Summary); Frances A., Universidad Politécnica de Madrid; Asensi R., Universidad Politécnica de Madrid; Garcia O., Universidad Politécnica de Madrid; Prieto R., Universidad Politécnica de Madrid; Uceda J., Universidad Politécnica de Madrid (Authors with Filk) | E55: Analytical models; Dc-dc power converters; Interconnected systems; Microgrids; Nonlinear dynamical systems; Power system modeling; Smart grids; System dynamics; System identification; System performance | F55: Computer Science (Miscellaneous) | G55: Electronic power converters (EPCs) are the key elements of the smart dc microgrid architectures. In order to enhance the controllability of the system, most of the elements are envisioned to be connected to the different buses through EPCs. Therefore, power flow, stability, and dynamic response in the microgrid are function of the behavior of the EPCs and their control loops. Besides, dc microgrids constitute a new paradigm in power distribution systems due to the high variability of their operating conditions, owing to the intermittent behavior of the renewable sources and customer energy consumption. Furthermore, in order to deal with this variability, the power converters can modify their operation mode, adding complexity to the dynamic and stability analysis of the system. This paper gives an overview of the various analytical and blackbox modeling strategies applied to smart dc micro/nanogrids. Different linear and nonlinear modeling techniques are reviewed describing their capabilities, but also their limitations. Finally, differences among blackbox models will be highlighted by means of illustrative examples. | H55: 9 | I55: 2 | J55: modeling electronic power converters in smart dc microgrids an overview
A56: 60 | B56: Blackbox Large-Signal Modeling of Grid-Connected DC-AC Electronic Power Converters | C56: 2019-01-01 | D56: Modern electric power distribution systems are progressively integrating electronic power converters. However, the design of electronic-power-converter-based systems is not a straightforward task, as the interactions among the different converters can lead to dynamic degradation or instabilities. In addition, electric power distribution systems are expected to consist of commercial-off-the-shelf converters, which implies limited information about the dynamic behavior of the devices. Large-signal blackbox modeling approaches have been proposed in order to obtain accurate dynamic models of commercial converters that can be used for system-level analyses. However, most of the works are focused on DC-DC converters. In this work, a large-signal blackbox model is proposed to model grid-connected three-phase DC-AC converters. An experimental setup has been used to demonstrate the limitations of small-signal models and the capability of the proposed modeling approach to capture the dynamic behavior of the converter when large perturbations are applied. Finally, the automation of the model identification process is discussed. (Summary); Univ Politecn Madrid, Ctr Elect Ind, E-28006 Madrid, Spain. gfguarderas@espe.edu.ec; airan.frances@upm.es; dionisio.ramirez@upm.es; rafael.asensi@upm.es; javier.uceda@upm.es (Author of contact); This research was funded by the Spanish Ministry of Economy and Competitiveness under the Project IDENMRED with reference DPI2016-78644-P. (Recognitions linked to item) | E56: Dc-ac power converters; Nonlinear dynamical systems; System identification | F56: Control and Optimization | G56: Modern electric power distribution systems are progressively integrating electronic power converters. However, the design of electronic-power-converter-based systems is not a straightforward task, as the interactions among the different converters can lead to dynamic degradation or instabilities. In addition, electric power distribution systems are expected to consist of commercial-off-the-shelf converters, which implies limited information about the dynamic behavior of the devices. Large-signal blackbox modeling approaches have been proposed in order to obtain accurate dynamic models of commercial converters that can be used for system-level analyses. However, most of the works are focused on DC-DC converters. In this work, a large-signal blackbox model is proposed to model grid-connected three-phase DC-AC converters. An experimental setup has been used to demonstrate the limitations of small-signal models and the capability of the proposed modeling approach to capture the dynamic behavior of the converter when large perturbations are applied. Finally, the automation of the model identification process is discussed. | H56: 9 | I56: 2 | J56: blackbox largesignal modeling of gridconnected dcac electronic power converters
A57: 62 | B57: Discrete-time systems sliding mode switching hyperplane design: A survey | C57: 2019-05-01 | D57: As regards to variable structure control with sliding mode (VSC-SM), it is known that designing sliding surface is a critical task because sliding surfaces must guarantee that the steady state of the controlled system achieves some desired performance including global (or global asymptotic) stability. This problem has been extensively analyzed for a wide class of systems: scalar, multivariable, linear, nonlinear, time-variant, discrete-time system, etc. The main purpose of this paper is to present a thorough survey about the main approaches related to the design of discrete-time switching surfaces applied to VSC-SM. Research works covering the design of sliding surfaces for the aforementioned systems are considered and some illustrative examples are also included to explain some of the design methodologies. (Summary); UPM, CSIC, Ctr Automat & Robot, Intelligent Control Grp, Madrid 28500, Spain. jd.luis@alumnos.upm.es (Author of contact); Spanish Ministry of Science, Innovation and Universities, Grant/Award Number: DPI2017-86915-C3-3-R (Recognitions linked to item) | E57: Boiler; Control scheme; Discrete sliding mode; Dynamics; Existence; Nonlinear control; Nonlinear-systems; Robust-control; State; Surface design; Switching surface; Uncertain systems; Variable structure control; Variable-structure control | F57: Control and Optimization | G57: As regards to variable structure control with sliding mode (VSC-SM), it is known that designing sliding surface is a critical task because sliding surfaces must guarantee that the steady state of the controlled system achieves some desired performance including global (or global asymptotic) stability. This problem has been extensively analyzed for a wide class of systems: scalar, multivariable, linear, nonlinear, time-variant, discrete-time system, etc. The main purpose of this paper is to present a thorough survey about the main approaches related to the design of discrete-time switching surfaces applied to VSC-SM. Research works covering the design of sliding surfaces for the aforementioned systems are considered and some illustrative examples are also included to explain some of the design methodologies. | H57: 9 | I57: 2 | J57: discretetime systems sliding mode switching hyperplane design a survey
A58: 63 | B58: Ultraefficient Voltage Doubler Based on a GaN Resonant Switched-Capacitor Converter | C58: 2019-06-01 | D58: © 2013 IEEE. In this paper, we present a highly efficient and compact voltage doubler based on a resonant switched-capacitor converter implemented with GaN FETs. Two possible approaches for its implementation are analyzed and compared. In the first approach, the resonant inductor is placed in series with a resonant capacitor, conducting a sinusoidal current, while in the second, it is placed in series with the input source, conducting rectified sinusoidal current. Both resonant converters have the same voltage gain, and although the change in the position of the resonant inductor is, at the first glance, of minor importance, the analysis and results show that it has huge impact on the capability to achieve zero-voltage switching (ZVS) transitions at low output power. The experimental results clearly show that at low loads when the resonant inductor is in series with the resonant capacitor, the switching frequency can be significantly higher than the resonant frequency and that it is, practically, impossible to achieve ZVS transitions, forcing the implementation of cycle skipping. The prototype implemented for the experiments can provide up to 4.5-kW losing between 20 and 22 W. In the case of light load (500 W), the power losses were only 2-3 W. Its power density is higher than 65 kW/dm 3 . The same resonant converter was tested with Si CoolMOS devices as well and the impact of the semiconductor technology on the overall power losses was verified. Due to higher C-{mathrm {oss}} capacitance, the Si-based converter has 40% higher power losses at full power than its GaN-based counterpart. The components of the GaN-based converter occupy only 65 cm 3 , which opens a possibility to obtain a design with extremely high power density. (Summary); Vasic M., Universidad Politécnica de Madrid; Serrano D., Universidad Politécnica de Madrid; Toral V., Universidad Politécnica de Madrid; Alou P., Universidad Politécnica de Madrid; Oliver J., Universidad Politécnica de Madrid; Cobos J., Universidad Politécnica de Madrid (Authors with Filk) | E58: Capacitors; Design; Gallium nitride; Inductors; Litz-wire; Resonant converters; Switched capacitors; Switches; Switching frequency; Transistors; Zero voltage switching; Zero-voltage switching (zvs) | F58: Electrical and Electronic Engineering | G58: In this paper, we present a highly efficient and compact voltage doubler based on a resonant switched-capacitor converter implemented with GaN FETs. Two possible approaches for its implementation are analyzed and compared. In the first approach, the resonant inductor is placed in series with a resonant capacitor, conducting a sinusoidal current, while in the second, it is placed in series with the input source, conducting rectified sinusoidal current. Both resonant converters have the same voltage gain, and although the change in the position of the resonant inductor is, at the first glance, of minor importance, the analysis and results show that it has huge impact on the capability to achieve zero-voltage switching (ZVS) transitions at low output power. The experimental results clearly show that at low loads when the resonant inductor is in series with the resonant capacitor, the switching frequency can be significantly higher than the resonant frequency and that it is, practically, impossible to achieve ZVS transitions, forcing the implementation of cycle skipping. The prototype implemented for the experiments can provide up to 4.5-kW losing between 20 and 22 W. In the case of light load (500 W), the power losses were only 2-3 W. Its power density is higher than 65 kW/dm 3 . The same resonant converter was tested with Si CoolMOS devices as well and the impact of the semiconductor technology on the overall power losses was verified. Due to higher C-{mathrm {oss}} capacitance, the Si-based converter has 40% higher power losses at full power than its GaN-based counterpart. The components of the GaN-based converter occupy only 65 cm 3 , which opens a possibility to obtain a design with extremely high power density. | H58: 9 | I58: 2 | J58: ultraefficient voltage doubler based on a gan resonant switchedcapacitor converter
A59: 65 | B59: A training system for Industry 4.0 operators in complex assemblies based on virtual reality and process mining | C59: 2019-10-01 | D59: © 2019 Elsevier Ltd Industry 4.0 aims at integrating machines and operators through network connections and information management. It proposes the use of a set of technologies in industry, such as data analysis, Internet of Things, cloud computing, cooperative robots, and immersive technologies. This paper presents a training system for industrial operators in assembly tasks, which takes advantage of tools such as virtual reality and process mining. First, expert workers use an immersive interface to perform assemblies according to their experience. Then, process mining algorithms are applied to obtain assembly models from event logs. Finally, trainee workers use an improved immersive interface with hints to learn the assemblies that the expert workers introduced in the system. A toy example has been developed with building blocks and tests have been performed with a set of volunteers. The results show that the proposed training system, based on process mining and virtual reality, is competitive against conventional alternatives. Furthermore, user evaluations are better in terms of mental demand, perception, learning, results, and performance. (Summary); Roldán J., Universidad Politécnica de Madrid; Crespo E., Universidad Politécnica de Madrid; Martín-Barrio A., Universidad Politécnica de Madrid; Peña-Tapia E., Universidad Politécnica de Madrid; Barrientos A., Universidad Politécnica de Madrid (Authors with Filk) | E59: Assemblies; Industry 4.0; Missions; Process mining; Simulation; Training system; Virtual reality | F59: Software | G59: 0 aims at integrating machines and operators through network connections and information management. It proposes the use of a set of technologies in industry, such as data analysis, Internet of Things, cloud computing, cooperative robots, and immersive technologies. This paper presents a training system for industrial operators in assembly tasks, which takes advantage of tools such as virtual reality and process mining. First, expert workers use an immersive interface to perform assemblies according to their experience. Then, process mining algorithms are applied to obtain assembly models from event logs. Finally, trainee workers use an improved immersive interface with hints to learn the assemblies that the expert workers introduced in the system. A toy example has been developed with building blocks and tests have been performed with a set of volunteers. The results show that the proposed training system, based on process mining and virtual reality, is competitive against conventional alternatives. Furthermore, user evaluations are better in terms of mental demand, perception, learning, results, and performance. | H59: 9 | I59: 2 | J59: a training system for industry 40 operators in complex assemblies based on virtual reality and process mining
A60: 66 | B60: Multi-Output Conditional Inference Trees Applied to the Electricity Market: Variable Importance Analysis | C60: 2019-03-21 | D60: Predicting electricity prices and demand is a very important issue for the energy market industry. In order to improve the accuracy of any predictive model, a previous variable importance analysis is highly advised. In this paper, we propose an alternative framework to assess the variable importance in multivariate response scenarios based on the permutation importance technique, applying the Conditional inference trees algorithm and a phi-divergence measure. Our solution was tested in simulated examples as well as a real case, where we assessed and ranked the most relevant predictors for price and demand of electricity jointly in the Spanish market. The new method outperforms, in most cases, the outcomes achieved by the recently proposed techniques, Intervention prediction measure (IPM) and Sequential multi-response feature selection (SMuRFS). For the electricity market case, we identified the most relevant predictors among pollutant, renewable, calendar and lagged prices variables for the joint response of demand and price, showing also the effectiveness of the proposed multivariate response method when compared with the univariate response analysis. (Summary); Univ Politecn Madrid, Escuela Tecn Super Ingenieros Ind, C Jose Gutierrez Abascal 2, E-28006 Madrid, Spain. ismael.ahrazem.dfuf@alumnos.upm.es; josemanuel.mira@upm.es; camino.gonzalez@upm.es (Author of contact) | E60: Arima; Conditional inference trees; Electricity market; Energy; F-divergence measure; Feature-selection; Fundamentals; Impact; Models; Multivariate response; Phi-divergence measure; Price; Random forest; Regression trees; Sensitivity indexes; Variable importance measure | F60: Control and Optimization | G60: Predicting electricity prices and demand is a very important issue for the energy market industry. In order to improve the accuracy of any predictive model, a previous variable importance analysis is highly advised. In this paper, we propose an alternative framework to assess the variable importance in multivariate response scenarios based on the permutation importance technique, applying the Conditional inference trees algorithm and a phi-divergence measure. Our solution was tested in simulated examples as well as a real case, where we assessed and ranked the most relevant predictors for price and demand of electricity jointly in the Spanish market. The new method outperforms, in most cases, the outcomes achieved by the recently proposed techniques, Intervention prediction measure (IPM) and Sequential multi-response feature selection (SMuRFS). For the electricity market case, we identified the most relevant predictors among pollutant, renewable, calendar and lagged prices variables for the joint response of demand and price, showing also the effectiveness of the proposed multivariate response method when compared with the univariate response analysis. | H60: 7 | I60: 2 | J60: multioutput conditional inference trees applied to the electricity market variable importance analysis
A61: 67 | B61: APPLICATION OF AN ACTIVE RECTIFIER USED TO MITIGATE CURRENTS DISTORTION IN 6-10 KV DISTRIBUTION GRIDS | C61: 2019-01-01 | D61: The paper addresses issues of using the active rectifier in partially loaded variable frequency drive as active filter in the conditions of non-sinusoidal current and voltage disturbances caused by the presence of high-power non-linear load in the grid. The topology of transformless three-level converter for 6-10 kV suitable for proposed solution has been presented and its mathematical model has been de-rived. Based on the model, the direct power control algorithm with ability to compensate non-linear currents has been designed. The investigation of active rectifier efficiency was performed depending on the relation between linear and non-linear load currents of the grid node, as well as on active power load of the active rectifier. Efficiency analysis was based on the developed computer model of the grid node with connected non-linear load simultaneously with the variable frequency drive with active rectifier. (Summary); Univ Politecn Madrid, Madrid, Spain. jmguijosa@etsii.upm.es; kryltcov@outlook.com; forsakenfour@gmail.com (Author of contact) | E61: Active filtering; Active rectifier; Demand-controlled ventilation; Direct power control; Direct power-control; Harmonic disturbance; Motor | F61: Geotechnical Engineering and Engineering Geology | G61: The paper addresses issues of using the active rectifier in partially loaded variable frequency drive as active filter in the conditions of non-sinusoidal current and voltage disturbances caused by the presence of high-power non-linear load in the grid. The topology of transformless three-level converter for 6-10 kV suitable for proposed solution has been presented and its mathematical model has been de-rived. Based on the model, the direct power control algorithm with ability to compensate non-linear currents has been designed. The investigation of active rectifier efficiency was performed depending on the relation between linear and non-linear load currents of the grid node, as well as on active power load of the active rectifier. Efficiency analysis was based on the developed computer model of the grid node with connected non-linear load simultaneously with the variable frequency drive with active rectifier. | H61: 7 | I61: 2 | J61: application of an active rectifier used to mitigate currents distortion in 610 kv distribution grids
... A70: 76 | B70: Development of a versatile biotinylated material based on SU-8 | C70: 2013-06-07 | D70: The negative epoxy-based SU-8 photoresist has a wide variety of applications within the semiconductor industry, photonics and lab-on-a-chip devices, and it is emerging as an alternative to silicon-based devices for sensing purposes. In the present work, biotinylation of the SU-8 polymer surface promoted by light is reported. As a result, a novel, effective, and low-cost material, focusing on the immobilization of bioreceptors and consequent biosensing, is developed. This material allows the spatial discrimination depending on the irradiation of desired areas. The most salient feature is that the photobiotin may be directly incorporated into the SU-8 curing process, consequently reducing time and cost. The potential use of this substrate is demonstrated by the immunoanalytical detection of the synthetic steroid gestrinone, showing excellent performances. Moreover, the naked eye biodetection due to the transparent SU-8 substrate, and simple instrumental quantification are additional advantages. (Summary); Univ Politecn Valencia, Ctr Reconocimiento Mol & Desarrollo Tecnol, Dept Quim, Camino Vera S-N, E-46071 Valencia, Spain. rpuchades@qim.upv.es (Author of contact); Financial support from Ministerio de Economia y Competitividad (MINECO TEC2012-31145) is acknowledged. (Recognitions linked to item) | E70: Assays; Biomolecules; Dna; Fabrication; Immobilization; Mems; Microstructures; Photolithography; Photoresist; Surface modification | F70: Medicine (Miscellaneous) | G70: The negative epoxy-based SU-8 photoresist has a wide variety of applications within the semiconductor industry, photonics and lab-on-a-chip devices, and it is emerging as an alternative to silicon-based devices for sensing purposes. In the present work, biotinylation of the SU-8 polymer surface promoted by light is reported. As a result, a novel, effective, and low-cost material, focusing on the immobilization of bioreceptors and consequent biosensing, is developed. This material allows the spatial discrimination depending on the irradiation of desired areas. The most salient feature is that the photobiotin may be directly incorporated into the SU-8 curing process, consequently reducing time and cost. The potential use of this substrate is demonstrated by the immunoanalytical detection of the synthetic steroid gestrinone, showing excellent performances. Moreover, the naked eye biodetection due to the transparent SU-8 substrate, and simple instrumental quantification are additional advantages. | H70: 3 | I70: 1 | J70: development of a versatile biotinylated material based on su8
A71: 77 | B71: Propagation of Cross-Section Uncertainties in Criticality Calculations in the Framework of UAM-Phase I Using MCNPX-2.7e and SCALE-6.1 | C71: 2013-04-29 | D71: In the framework of the OECD/NEA project on Benchmark for Uncertainty Analysis in Modeling (UAM) for Design, Operation, and Safety Analysis of LWRs, several approaches and codes are being used to deal with the exercises proposed in Phase I, Specifications and Support Data for Neutronics Cases. At UPM, our research group treats these exercises with sensitivity calculations and the sandwich formula to propagate cross-section uncertainties. Two different codes are employed to calculate the sensitivity coefficients of k(eff) to cross sections in criticality calculations: MCNPX-2.7e and SCALE-6.1. The former uses the Differential Operator Technique and the latter uses the Adjoint-Weighted Technique. In this paper, the main results for exercise I-2 Lattice Physics are presented for the criticality calculations of PWR. These criticality calculations are done for a 15 x 15 TMI fuel assembly at four different states: HZP-Unrodded, HZP-Rodded, HFP-Unrodded, and HFP-Rodded. The results of the two different codes above are presented and compared. The comparison proves a good agreement between SCALE-6.1 and MCNPX-2.7e in k(eff) uncertainty that comes from the sensitivity coefficients calculated by both codes. Differences are found when the sensitivity profiles are analysed, but they do not lead to differences in the k(eff) uncertainty. (Summary); Univ Politecn Madrid, Dept Nucl Engn, C Jose Gutierrez Abascal 2, E-28006 Madrid, Spain. cj.diez@upm.es (Author of contact); The research leading to these results has received funding from specific collaborative agreement P110530207 between CSN and UPM in the area of uncertainty propagation in nuclear criticality safety. Also, this work is also partially supported by the Spanish Ministry of Education of Spain through the FPU Program for teaching and researching formation under Grant AP2009-1801 for the first author. (Recognitions linked to item) | F71: Nuclear Energy and Engineering | G71: In the framework of the OECD/NEA project on Benchmark for Uncertainty Analysis in Modeling (UAM) for Design, Operation, and Safety Analysis of LWRs, several approaches and codes are being used to deal with the exercises proposed in Phase I, Specifications and Support Data for Neutronics Cases. At UPM, our research group treats these exercises with sensitivity calculations and the sandwich formula to propagate cross-section uncertainties. Two different codes are employed to calculate the sensitivity coefficients of k(eff) to cross sections in criticality calculations: MCNPX-2.7e and SCALE-6.1. The former uses the Differential Operator Technique and the latter uses the Adjoint-Weighted Technique. In this paper, the main results for exercise I-2 Lattice Physics are presented for the criticality calculations of PWR. These criticality calculations are done for a 15 x 15 TMI fuel assembly at four different states: HZP-Unrodded, HZP-Rodded, HFP-Unrodded, and HFP-Rodded. The results of the two different codes above are presented and compared. The comparison proves a good agreement between SCALE-6.1 and MCNPX-2.7e in k(eff) uncertainty that comes from the sensitivity coefficients calculated by both codes. Differences are found when the sensitivity profiles are analysed, but they do not lead to differences in the k(eff) uncertainty. | H71: 7 | I71: 2 | J71: propagation of crosssection uncertainties in criticality calculations in the framework of uamphase i using mcnpx27e and scale61
A72: 78 | B72: The interurban DRAG-Spain model: The main factors of influence on road accidents in Spain | C72: 2013-01-01 | D72: This paper presents the results of applying DRAG methodology to the identification of the main factors of influence on the number of injury and fatal accidents occurring on Spain's interurban network. Nineteen independent variables have been included in the model grouped together under ten categories: exposure, infrastructure, weather, drivers, economic variables, vehicle stock, surveillance, speed and legislative measures. Highly interesting conclusions can be reached from the results on the basis of the different effects of a single variable on each of the accident types according to severity. The greatest influence revealed by the results is exposure, which together with inexperienced drivers, speed and an ageing vehicle stock, have a negative effect, while the increased surveillance on roads, the improvement in the technological features of vehicles and the proportion of high capacity networks have a positive effect, since the results obtained show a significant drop in accidents. (C) 2011 Elsevier Ltd. All rights reserved. (Summary); INSIA, Automobile Res Inst, Madrid, Spain. francisco.aparicio@upm.es; barenas@etsii.upm.es; ebernardos@etsii.upm.es (Author of contact); This research with reference TRA-2004-07886/AUT was financed by the 2004-2007 National research and Development Plan, the Government's General Traffic Directorate and the Spanish Association of Automobile and Lorry Manufacturers (ANFAC). The project is part of the SEGVAUTO project framework, of the Madrid Regional Government. The research team would like to thank Marc Gaudry for his comments and recommendations that have contributed to improving the I-DE model. (Recognitions linked to item) | E72: Infrastructure; Mobility; Safety laws; Spanish intercity road network; Surveillance; Time series analysis; Traffic accidents; Traffic speed; Vehicle stock characteristics | F72: Economics, Econometrics and Finance (Miscellaneous) | G72: This paper presents the results of applying DRAG methodology to the identification of the main factors of influence on the number of injury and fatal accidents occurring on Spain's interurban network. Nineteen independent variables have been included in the model grouped together under ten categories: exposure, infrastructure, weather, drivers, economic variables, vehicle stock, surveillance, speed and legislative measures. Highly interesting conclusions can be reached from the results on the basis of the different effects of a single variable on each of the accident types according to severity. The greatest influence revealed by the results is exposure, which together with inexperienced drivers, speed and an ageing vehicle stock, have a negative effect, while the increased surveillance on roads, the improvement in the technological features of vehicles and the proportion of high capacity networks have a positive effect, since the results obtained show a significant drop in accidents. | H72: 3 | I72: 1 | J72: the interurban dragspain model the main factors of influence on road accidents in spain
A73: 79 | B73: Presentation and Discussion of the UAM/Exercise I-1b: "Pin-Cell Burn-Up Benchmark" with the Hybrid Method | C73: 2013-03-11 | D73: The aim of this work is to present the Exercise I-1b pin-cell burn-up benchmark proposed in the framework of OECD LWR UAM. Its objective is to address the uncertainty due to the basic nuclear data as well as the impact of processing the nuclear and covariance data in a pin-cell depletion calculation. Four different sensitivity/uncertainty propagation methodologies participate in this benchmark (GRS, NRG, UPM, and SNU& KAERI). The paper describes the main features of the UPM model (hybrid method) compared with other methodologies.. e requested output provided by UPM is presented, and it is discussed regarding the results of other methodologies. (Summary); Univ Politecn Madrid, Dept Nucl Engn, C Jose Gutierrez Abascal 2, E-28006 Madrid, Spain. oscar.cabellos@upm.es (Author of contact) | E73: Nuclear-data uncertainties; Propagation | F73: Nuclear Energy and Engineering | G73: The aim of this work is to present the Exercise I-1b pin-cell burn-up benchmark proposed in the framework of OECD LWR UAM. Its objective is to address the uncertainty due to the basic nuclear data as well as the impact of processing the nuclear and covariance data in a pin-cell depletion calculation. Four different sensitivity/uncertainty propagation methodologies participate in this benchmark (GRS, NRG, UPM, and SNU& KAERI). The paper describes the main features of the UPM model (hybrid method) compared with other methodologies.. e requested output provided by UPM is presented, and it is discussed regarding the results of other methodologies. | H73: 9 | I73: 2 | J73: presentation and discussion of the uamexercise i1b pincell burnup benchmark with the hybrid method
A74: 81 | B74: Vulnerability analysis of RC buildings with wide beams located in moderate seismicity regions | C74: 2013-01-01 | D74: A significant number of short-to-mid height RC buildings with wide beams have been constructed in areas of moderate seismicity of Spain, mainly for housing and administrative use. The buildings have a framed structure with one-way slabs; the wide beams constitute the distinctive characteristic, their depth being equal to that of the rest of the slab, thus providing a flat lower surface, convenient for construction and the layout of facilities. Seismic behavior in the direction of the wide beams appears to be deficient because of: (i) low lateral strength, mainly because of the small effective depth of the beams, (ii) inherent low ductility of the wide beams, generated by high amount of reinforcement, (iii) the big strut compressive forces developed inside the column-beam connections due to the low height of the beams, and (iv) the fact that the wide beams are wider than the columns, meaning that the contribution of the outer zones to the resistance of the beam-column joints is unreliable because there is no torsion reinforcement. In the orthogonal direction, the behavior is worse since the only members of the slabs that contribute to the lateral resistance are the joists and the facade beams. Moreover, these buildings were designed with codes that did not include ductility requirements and required only a low lateral resistance; indeed, in many cases, seismic action was not considered at all. Consequently, the seismic capacity of these structures is not reliable. The objective of this research is to assess numerically this capability, whereas further research will aim to propose retrofit strategies. The research approach consists of: (i) selecting a number of 3-story and 6-story buildings that represent the vast majority of the existing ones and (ii) evaluating their vulnerability through three types of analyses, namely: code-type, push-over and nonlinear dynamic analysis. Given the low lateral resistance of the main frames, the cooperation of the masonry infill walls is accounted for; for each representative building, three wall densities are considered. The results of the analyses show that the buildings in question exhibit inadequate seismic behavior in most of the examined situations. In general, the relative performance is less deficient for Target Drift CP (Collapse Prevention) than for IO (Immediate Occupancy). Since these buildings are selected to be representative of the vast majority of buildings with wide beams that were constructed in Spain without accounting for any seismic consideration, our conclusions can be extrapolated to a broader scenario. (c) 2012 Elsevier Ltd. All rights reserved. (Summary); Tech Univ Catalonia, Architecture Struct Dept, Avda Diagonal 649, Barcelona 08028, Spain. francesc.lopez-almansa@upc.edu (Author of contact); This work has received financial support from the Spanish Government under projects CGL2008-00869/BTE, CGL2011-23621, BIA2008-00050 and BIA2011-26816 and from the European Union (Feder). (Recognitions linked to item) | E74: Behavior; Column connections; Concrete buildings; Push-over analysis; Reinforced-concrete; Seismic vulnerability; Spain; Wide beams | F74: Civil and Structural Engineering | G74: A significant number of short-to-mid height RC buildings with wide beams have been constructed in areas of moderate seismicity of Spain, mainly for housing and administrative use. The buildings have a framed structure with one-way slabs; the wide beams constitute the distinctive characteristic, their depth being equal to that of the rest of the slab, thus providing a flat lower surface, convenient for construction and the layout of facilities. Seismic behavior in the direction of the wide beams appears to be deficient because of: (i) low lateral strength, mainly because of the small effective depth of the beams, (ii) inherent low ductility of the wide beams, generated by high amount of reinforcement, (iii) the big strut compressive forces developed inside the column-beam connections due to the low height of the beams, and (iv) the fact that the wide beams are wider than the columns, meaning that the contribution of the outer zones to the resistance of the beam-column joints is unreliable because there is no torsion reinforcement. In the orthogonal direction, the behavior is worse since the only members of the slabs that contribute to the lateral resistance are the joists and the facade beams. Moreover, these buildings were designed with codes that did not include ductility requirements and required only a low lateral resistance; indeed, in many cases, seismic action was not considered at all. Consequently, the seismic capacity of these structures is not reliable. The objective of this research is to assess numerically this capability, whereas further research will aim to propose retrofit strategies. The research approach consists of: (i) selecting a number of 3-story and 6-story buildings that represent the vast majority of the existing ones and (ii) evaluating their vulnerability through three types of analyses, namely: code-type, push-over and nonlinear dynamic analysis. Given the low lateral resistance of the main frames, the cooperation of the masonry infill walls is accounted for; for each representative building, three wall densities are considered. The results of the analyses show that the buildings in question exhibit inadequate seismic behavior in most of the examined situations. In general, the relative performance is less deficient for Target Drift CP (Collapse Prevention) than for IO (Immediate Occupancy). Since these buildings are selected to be representative of the vast majority of buildings with wide beams that were constructed in Spain without accounting for any seismic consideration, our conclusions can be extrapolated to a broader scenario. (c) 2012 Elsevier Ltd. All rights reserved. | H74: 9 | I74: 2 | J74: vulnerability analysis of rc buildings with wide beams located in moderate seismicity regions
A75: 82 | B75: Social identity changes in networked organizations | C75: 2013-01-01 | D75: Organizations are experiencing strategic, cultural and organizational changes in order to adapt themselves to the Information Society. Incorporating Information and Communication Technologies (ICTs) allow for network schemes of work for employees (including telecommuting) and staff virtualization. In this new context, systems of meaning change and the social identity of the staff is affected. This paper analyses how social identity evolves and how it is related to affiliation needs by studying a group of 205 professionals with different characteristics, divided into network and non-network professionals. In turn, these professionals belonged to organizations, which depending on certain characteristics, have been categorized as more or less virtual. Two main research results emerge. The first is an analytical methodology for networked organizations. The second is the confirmation that social identity weakens for professionals with high affiliation needs when virtualization occurs in an organization. (Summary); Univ Politecn Madrid, Escuela Tecn Super Ingn Ind, C Jose Gutierrez Abascal 2, E-28006 Madrid, Spain. ana.moreno.romero@upm.es (Author of contact) | E75: Identification; Network professional; Networked organization; Networks; Social identity; Virtual organization; Work | F75: Social Psychology | G75: Organizations are experiencing strategic, cultural and organizational changes in order to adapt themselves to the Information Society. Incorporating Information and Communication Technologies (ICTs) allow for network schemes of work for employees (including telecommuting) and staff virtualization. In this new context, systems of meaning change and the social identity of the staff is affected. This paper analyses how social identity evolves and how it is related to affiliation needs by studying a group of 205 professionals with different characteristics, divided into network and non-network professionals. In turn, these professionals belonged to organizations, which depending on certain characteristics, have been categorized as more or less virtual. Two main research results emerge. The first is an analytical methodology for networked organizations. The second is the confirmation that social identity weakens for professionals with high affiliation needs when virtualization occurs in an organization. | H75: 8 | I75: 0 | J75: social identity changes in networked organizations
A76: 83 | B76: Variable Structure Control with Chattering Reduction of a Generalized T-S Model | C76: 2013-01-01 | D76: In this paper, a fuzzy logic controller (FLC) based variable structure control (VSC) is presented. The main objective is to obtain an improved performance of highly non-linear unstable systems. New functions for chattering reduction and error convergence without sacrificing invariant properties are proposed. The main feature of the proposed method is that the switching function is added as an additional fuzzy variable and will be introduced in the premise part of the fuzzy rules; together with the state variables. In this work, a tuning of the well known weighting parameters approach is proposed to optimize local and global approximation and modelling capability of the Takagi-Sugeno (T-S) fuzzy model to improve the choice of the performance index and minimize it. The main problem encountered is that the T-S identification method can not be applied when the membership functions are overlapped by pairs. This in turn restricts the application of the T-S method because this type of membership function has been widely used in control applications. The approach developed here can be considered as a generalized version of the T-S method. An inverted pendulum mounted on a cart is chosen to evaluate the robustness, effectiveness, accuracy and remarkable performance of the proposed estimation approach in comparison with the original T-S model. Simulation results indicate the potential, simplicity and generality of the estimation method and the robustness of the chattering reduction algorithm. In this paper, we prove that the proposed estimation algorithm converge the very fast, thereby making it very practical to use. The application of the proposed FLC-VSC shows that both alleviation of chattering and robust performance are achieved. (Summary); Univ Politecn Madrid, Intelligent Control Grp, E-28040 Madrid, Spain. (Author of contact); This work is funded by Spanish Ministry of innovation and Science (ARABOT project DPI2010-21247-C02-01). (Recognitions linked to item) | E76: Design; Filter; Fuzzy rule interpolation; Fuzzy systems; Identification; Membership functions; Nonlinear systems; Parameters' weighting method; Systems; Takagi-sugeno fuzzy model; Universal approximators; Variable structure control | F76: Control and Systems Engineering | G76: In this paper, a fuzzy logic controller (FLC) based variable structure control (VSC) is presented. The main objective is to obtain an improved performance of highly non-linear unstable systems. New functions for chattering reduction and error convergence without sacrificing invariant properties are proposed. The main feature of the proposed method is that the switching function is added as an additional fuzzy variable and will be introduced in the premise part of the fuzzy rules; together with the state variables. In this work, a tuning of the well known weighting parameters approach is proposed to optimize local and global approximation and modelling capability of the Takagi-Sugeno (T-S) fuzzy model to improve the choice of the performance index and minimize it. The main problem encountered is that the T-S identification method can not be applied when the membership functions are overlapped by pairs. This in turn restricts the application of the T-S method because this type of membership function has been widely used in control applications. The approach developed here can be considered as a generalized version of the T-S method. An inverted pendulum mounted on a cart is chosen to evaluate the robustness, effectiveness, accuracy and remarkable performance of the proposed estimation approach in comparison with the original T-S model. Simulation results indicate the potential, simplicity and generality of the estimation method and the robustness of the chattering reduction algorithm. In this paper, we prove that the proposed estimation algorithm converge the very fast, thereby making it very practical to use. The application of the proposed FLC-VSC shows that both alleviation of chattering and robust performance are achieved. | H76: 9 | I76: 2 | J76: variable structure control with chattering reduction of a generalized ts model
A77: 84 | B77: An Aerial-Ground Robotic System for Navigation and Obstacle Mapping in Large Outdoor Areas | C77: 2013-01-01 | D77: There are many outdoor robotic applications where a robot must reach a goal position or explore an area without previous knowledge of the environment around it. Additionally, other applications (like path planning) require the use of known maps or previous information of the environment. This work presents a system composed by a terrestrial and an aerial robot that cooperate and share sensor information in order to address those requirements. The ground robot is able to navigate in an unknown large environment aided by visual feedback from a camera on board the aerial robot. At the same time, the obstacles are mapped in real-time by putting together the information from the camera and the positioning system of the ground robot. A set of experiments were carried out with the purpose of verifying the system applicability. The experiments were performed in a simulation environment and outdoor with a medium-sized ground robot and a mini quad-rotor. The proposed robotic system shows outstanding results in simultaneous navigation and mapping applications in large outdoor environments. (Summary); UPM CSIC, Ctr Automat & Robot, Calle Jose Gutierrez Abascal 2, Madrid 28006, Spain. ma.garzon@upm.es; joao.valente@upm.es; david.zapata@etsii.upm.es; antonio.barrientos@upm.es (Author of contact); This work was supported by the Robotics and Cybernetics Group at Technical University of Madrid (Spain), and funded under the projects ROTOS: Multi-robot system for outdoor infrastructures protection, sponsored by Spanish Ministry of Education and Science (DPI2010-17998), and ROBOCITY 2030, sponsored by the Community of Madrid (S-0505/DPI/000235). (Recognitions linked to item) | E77: Autonomous navigation; Collaborative robotics; Cooperative perception; Obstacle avoidance; Outdoor mapping; Uav; Ugv | F77: Electrical and Electronic Engineering | G77: There are many outdoor robotic applications where a robot must reach a goal position or explore an area without previous knowledge of the environment around it. Additionally, other applications (like path planning) require the use of known maps or previous information of the environment. This work presents a system composed by a terrestrial and an aerial robot that cooperate and share sensor information in order to address those requirements. The ground robot is able to navigate in an unknown large environment aided by visual feedback from a camera on board the aerial robot. At the same time, the obstacles are mapped in real-time by putting together the information from the camera and the positioning system of the ground robot. A set of experiments were carried out with the purpose of verifying the system applicability. The experiments were performed in a simulation environment and outdoor with a medium-sized ground robot and a mini quad-rotor. The proposed robotic system shows outstanding results in simultaneous navigation and mapping applications in large outdoor environments. | H77: 9 | I77: 2 | J77: an aerialground robotic system for navigation and obstacle mapping in large outdoor areas
A78: 85 | B78: Silica final lens performance in laser fusion facilities: HiPER and LIFE | C78: 2013-01-01 | D78: Nowadays, the projects LIFE (Laser Inertial Fusion Energy) in USA and HiPER (High Power Laser Energy Research) in Europe are the most advanced ones to demonstrate laser fusion energy viability. One of the main points of concern to properly achieve ignition is the performance of the final optics (lenses) under the severe irradiation conditions that take place in fusion facilities. In this paper, we calculate the radiation fluxes and doses as well as the radiation-induced temperature enhancement and colour centre formation in final lenses assuming realistic geometrical configurations for HiPER and LIFE. On these bases, the mechanical stresses generated by the established temperature gradients are evaluated showing that from a mechanical point of view lenses only fulfil specifications if ions resulting from the imploding target are mitigated. The absorption coefficient of the lenses is calculated during reactor startup and steady-state operation. The obtained results reveal the necessity of new solutions to tackle ignition problems during the startup process for HiPER. Finally, we evaluate the effect of temperature gradients on focal length changes and lens surface deformations. In summary, we discuss the capabilities and weak points of silica lenses and propose alternatives to overcome predictable problems. (Summary); Univ Politecn Madrid, Inst Fus Nucl, Jose Gutierrez Abascal 2, E-28006 Madrid, Spain. david.garoz@upm.es (Author of contact); The authors thank the Spanish Ministry of Science and Innovation for economical support via ACI2009-1040 and AIC-A-2011-0718 projects. (Recognitions linked to item) | E78: Absorption; Chamber design; Dependence; Dry-wall; E centers; Energy life; Fused-silica; Generation; Glasses; Irradiation | F78: Nuclear and High Energy Physics | G78: Nowadays, the projects LIFE (Laser Inertial Fusion Energy) in USA and HiPER (High Power Laser Energy Research) in Europe are the most advanced ones to demonstrate laser fusion energy viability. One of the main points of concern to properly achieve ignition is the performance of the final optics (lenses) under the severe irradiation conditions that take place in fusion facilities. In this paper, we calculate the radiation fluxes and doses as well as the radiation-induced temperature enhancement and colour centre formation in final lenses assuming realistic geometrical configurations for HiPER and LIFE. On these bases, the mechanical stresses generated by the established temperature gradients are evaluated showing that from a mechanical point of view lenses only fulfil specifications if ions resulting from the imploding target are mitigated. The absorption coefficient of the lenses is calculated during reactor startup and steady-state operation. The obtained results reveal the necessity of new solutions to tackle ignition problems during the startup process for HiPER. Finally, we evaluate the effect of temperature gradients on focal length changes and lens surface deformations. In summary, we discuss the capabilities and weak points of silica lenses and propose alternatives to overcome predictable problems. | H78: 7 | I78: 2 | J78: silica final lens performance in laser fusion facilities hiper and life
A79: 86 | B79: Cross-Entropy Optimization for Scaling Factors of a Fuzzy Controller: A See-and-Avoid Approach for Unmanned Aerial Systems | C79: 2013-01-01 | D79: The Cross-Entropy (CE) is an efficient method for the estimation of rare-event probabilities and combinatorial optimization. This work presents a novel approach of the CE for optimization of a Soft-Computing controller. A Fuzzy controller was designed to command an unmanned aerial system (UAS) for avoiding collision task. The only sensor used to accomplish this task was a forward camera. The CE is used to reach a near-optimal controller by modifying the scaling factors of the controller inputs. The optimization was realized using the ROS-Gazebo simulation system. In order to evaluate the optimization a big amount of tests were carried out with a real quadcopter. (Summary); Univ Politecn Madrid, CAR, Madrid, Spain. miguelolivaresmendez@gmail.com; luis.mejias@qut.edu.au (Author of contact); The work reported in this paper is the consecution of several research stages at the Computer Vision Group - Universidad Politecnica de Madrid and at the Australian Reasearch Centre for Aerospace Automation - Queensland University of Technology (ARCAA-QUT). The authors would like to thank to Caja Madrid for the mobility research grant of one of the authors. This work has been sponsored by the Spanish Science and Technology Ministry under the grant CICYT DPI2010-20751-C02-01 and by the IRSES Program Marie Curie FP7 - PIRSES-GA-2009-230797 - ICPUAS (International Cooperation Program for Unmanned Aerial Systems Research and Development). (Recognitions linked to item) | E79: Computer vision; Cross-entropy; Fuzzy control; Fuzzy logic; Optimization; See and avoid; Sense and avoid; Uas; Uav; Visual servoing | F79: Artificial Intelligence | G79: The Cross-Entropy (CE) is an efficient method for the estimation of rare-event probabilities and combinatorial optimization. This work presents a novel approach of the CE for optimization of a Soft-Computing controller. A Fuzzy controller was designed to command an unmanned aerial system (UAS) for avoiding collision task. The only sensor used to accomplish this task was a forward camera. The CE is used to reach a near-optimal controller by modifying the scaling factors of the controller inputs. The optimization was realized using the ROS-Gazebo simulation system. In order to evaluate the optimization a big amount of tests were carried out with a real quadcopter. | H79: 9 | I79: 2 | J79: crossentropy optimization for scaling factors of a fuzzy controller a seeandavoid approach for unmanned aerial systems
A80: 87 | B80: Analysis of the influence of the plasma thermodynamic regime in the spectrally resolved and mean radiative opacity calculations of carbon plasmas in a wide range of density and temperature | C80: 2013-01-01 | D80: In this work the spectrally resolved, multigroup and mean radiative opacities of carbon plasmas are calculated for a wide range of plasma conditions which cover situations where corona, local thermodynamic and non-local thermodynamic equilibrium regimes are found. An analysis of the influence of the thermodynamic regime on these magnitudes is also carried out by means of comparisons of the results obtained from collisional-radiative, corona or Saha-Boltzmann equations. All the calculations presented in this work were performed using ABAKO/RAPCAL code. (C) 2012 Elsevier Ltd. All rights reserved. (Summary); Univ Las Palmas Gran Canaria, Dept Fis, Campus Tafira, Las Palmas Gran Canaria, Spain. jmgil@dfis.ulpgc.es (Author of contact); This work has been supported by the Research Project of the Spanish Government ((ENE2009-11208/FTN), by the Research Project of the Government of the Canary Islands (SolSubC200801000057) and also by the Keep in touch Project of the European Union. (Recognitions linked to item) | E80: Atomic data; Autoionization; Carbon plasmas; Code; Collisional-radiative steady state model; Equilibrium; Excitation; Model; Nlte and lte regimes; Nlte emissivities; Optically thin; Package; Radiative properties; Z elements | F80: Atomic and Molecular Physics, and Optics | G80: In this work the spectrally resolved, multigroup and mean radiative opacities of carbon plasmas are calculated for a wide range of plasma conditions which cover situations where corona, local thermodynamic and non-local thermodynamic equilibrium regimes are found. An analysis of the influence of the thermodynamic regime on these magnitudes is also carried out by means of comparisons of the results obtained from collisional-radiative, corona or Saha-Boltzmann equations. All the calculations presented in this work were performed using ABAKO/RAPCAL code. | H80: 7 | I80: 2 | J80: analysis of the influence of the plasma thermodynamic regime in the spectrally resolved and mean radiative opacity calculations of carbon plasmas in a wide range of density and temperature
A81: 88 | B81: Analysis of the traded volume drivers of the Iberian power futures market | C81: 2013-01-01 | D81: A comprehensive assessment of the liquidity development in the Iberian power futures market managed by OMIP (Operador do Mercado Iberico de Energia, Polo Portugues) in its first 4 years of existence is performed. This market started on July 2006. A regression model tracking the evolution of the traded volumes in the continuous market is built as a function of 12 potential liquidity drivers. The only significant drivers are the traded volumes in OMIP compulsory auctions, the traded volumes in the Over The Counter (OTC) market, and the OTC cleared volumes in OMIP clearing house (OMIClear). Furthermore, the enrollment of financial members shows strong correlation with the traded volumes in the continuous market. OMIP liquidity is still far from the levels reached by the most mature European markets (Nord Pool and EEX). The market operator and its clearing house could develop efficient marketing actions to attract new entrants active in the spot market (energy intensive industries, suppliers, and small producers) as well as volumes from the opaque OTC market, and to improve the performance of existing illiquid products. An active dialogue with all the stakeholders (market participants, spot market operator, and supervisory authorities) will help to implement such actions. (C) 2012 Elsevier Ltd. All rights reserved. (Summary); Tech Univ Madrid UPM, Dept Business Adm, Jose Gutierrez Abascal 2, Madrid 28006, Spain. alvarocapitan@hotmail.com; crmon-roy@etsii.tipm.es (Author of contact) | E81: Efficiency; Electricity sector; Energy regulation; Liquidity; Market supervision; Power futures market | F81: Energy Engineering and Power Technology | G81: A comprehensive assessment of the liquidity development in the Iberian power futures market managed by OMIP (Operador do Mercado Iberico de Energia, Polo Portugues) in its first 4 years of existence is performed. This market started on July 2006. A regression model tracking the evolution of the traded volumes in the continuous market is built as a function of 12 potential liquidity drivers. The only significant drivers are the traded volumes in OMIP compulsory auctions, the traded volumes in the Over The Counter (OTC) market, and the OTC cleared volumes in OMIP clearing house (OMIClear). Furthermore, the enrollment of financial members shows strong correlation with the traded volumes in the continuous market. OMIP liquidity is still far from the levels reached by the most mature European markets (Nord Pool and EEX). The market operator and its clearing house could develop efficient marketing actions to attract new entrants active in the spot market (energy intensive industries, suppliers, and small producers) as well as volumes from the opaque OTC market, and to improve the performance of existing illiquid products. An active dialogue with all the stakeholders (market participants, spot market operator, and supervisory authorities) will help to implement such actions. | H81: 7 | I81: 2 | J81: analysis of the traded volume drivers of the iberian power futures market
A82: 89 | B82: A Survey of Collective Movement of Mobile Robots | C82: 2013-01-29 | D82: Collective movement of mobile robots is the problem of how to control a group of robots making them move as a group, in a cohesive way, towards a common direction. Collective movement serves not only to move a group of robots from one point to another, but to perform more complex tasks such as using the group of robots as a moving sensor array, collective mapping and searching tasks. In this article, a survey of collective movement of mobile robots is done, including a classification and characterization of its different types, a review of the most important architectures and a list of its promising applications. (Summary); Univ Politecn Madrid, E-28040 Madrid, Spain. inaki.navarro@upm.es (Author of contact); This work is funded by the Spanish Ministry of Science and Technology (ARABOT: DPI 2010-21247-C02-01) and supervised by CACSA whose kindness we gratefully acknowledge. (Recognitions linked to item) | E82: Collective movement; Flocking; Robot formations; Swarms | F82: Artificial Intelligence | G82: Collective movement of mobile robots is the problem of how to control a group of robots making them move as a group, in a cohesive way, towards a common direction. Collective movement serves not only to move a group of robots from one point to another, but to perform more complex tasks such as using the group of robots as a moving sensor array, collective mapping and searching tasks. In this article, a survey of collective movement of mobile robots is done, including a classification and characterization of its different types, a review of the most important architectures and a list of its promising applications. | H82: 9 | I82: 2 | J82: a survey of collective movement of mobile robots
A83: 90 | B83: A New Simple Method for Estimating Exergy Destruction in Heat Exchangers | C83: 2013-01-01 | D83: This paper presents an abbreviated method for estimating exergy destruction in a heat exchanger, requiring only black-box data of the exchanger's inputs and outputs, and eliminating part of the mathematical difficulties associated with the calculations. A well-known model for temperature distributions in an exchanger is adapted for this case, and is used to distinguish between the contributions of the three major causes of the total exergetic loss: heat transfer, fluid friction and energy dissipation to the surroundings. This provides insight into the relative importance of the three, allowing for identification of potential improvements to a given design. (Summary); Univ Politecn Madrid, Energy & Fluid Mech Dept ETSII, JoseGutierrez Abascal 2, E-28006 Madrid, Spain. ignacio.lopez@upm.es; javier.rodriguez.martin@upm.es; celina.gonzalez@upm.es; a.jimenez@upm.es; rafael.nieto@upm.es (Author of contact) | E83: Heat exchanger; Heat transfer; Irreversibility; Second law analysis; Thermodynamics | F83: Physics and Astronomy (Miscellaneous) | G83: This paper presents an abbreviated method for estimating exergy destruction in a heat exchanger, requiring only black-box data of the exchanger's inputs and outputs, and eliminating part of the mathematical difficulties associated with the calculations. A well-known model for temperature distributions in an exchanger is adapted for this case, and is used to distinguish between the contributions of the three major causes of the total exergetic loss: heat transfer, fluid friction and energy dissipation to the surroundings. This provides insight into the relative importance of the three, allowing for identification of potential improvements to a given design. | H83: 9 | I83: 2 | J83: a new simple method for estimating exergy destruction in heat exchangers
... A145: 157 | B145: A Multiatlas Segmentation Using Graph Cuts with Applications to Liver Segmentation in CT Scans | C145: 2014-01-01 | D145: An atlas-based segmentation approach is presented that combines low-level operations, an affine probabilistic atlas, and a multiatlas-based segmentation. The proposed combination provides highly accurate segmentation due to registrations and atlas selections based on the regions of interest (ROIs) and coarse segmentations. Our approach shares the following common elements between the probabilistic atlas and multiatlas segmentation: (a) the spatial normalisation and (b) the segmentation method, which is based on minimising a discrete energy function using graph cuts. The method is evaluated for the segmentation of the liver in computed tomography (CT) images. Low-level operations define a ROI around the liver from an abdominal CT. We generate a probabilistic atlas using an affine registration based on geometry moments from manually labelled data. Next, a coarse segmentation of the liver is obtained from the probabilistic atlas with low computational effort. Then, a multiatlas segmentation approach improves the accuracy of the segmentation. Both the atlas selections and the nonrigid registrations of the multiatlas approach use a binary mask defined by coarse segmentation. We experimentally demonstrate that this approach performs better than atlas selections and nonrigid registrations in the entire ROI. The segmentation results are comparable to those obtained by human experts and to other recently published results. (Summary); Tech Univ Madrid, ETSIDI, Dept Comp Sci, Ronda Valencia 3, Madrid 28012, Spain. carlos.platero@upm.es (Author of contact) | E145: Atlas-based segmentation; Automatic liver; Brain mri segmentation; Construction; Image segmentation; Mutual information; Optimization; Probabilistic atlas; Registration; Selection | F145: Modeling and Simulation | G145: An atlas-based segmentation approach is presented that combines low-level operations, an affine probabilistic atlas, and a multiatlas-based segmentation. The proposed combination provides highly accurate segmentation due to registrations and atlas selections based on the regions of interest (ROIs) and coarse segmentations. Our approach shares the following common elements between the probabilistic atlas and multiatlas segmentation: (a) the spatial normalisation and (b) the segmentation method, which is based on minimising a discrete energy function using graph cuts. The method is evaluated for the segmentation of the liver in computed tomography (CT) images. Low-level operations define a ROI around the liver from an abdominal CT. We generate a probabilistic atlas using an affine registration based on geometry moments from manually labelled data. Next, a coarse segmentation of the liver is obtained from the probabilistic atlas with low computational effort. Then, a multiatlas segmentation approach improves the accuracy of the segmentation. Both the atlas selections and the nonrigid registrations of the multiatlas approach use a binary mask defined by coarse segmentation. We experimentally demonstrate that this approach performs better than atlas selections and nonrigid registrations in the entire ROI. The segmentation results are comparable to those obtained by human experts and to other recently published results. | H145: 3 | I145: 1 | J145: a multiatlas segmentation using graph cuts with applications to liver segmentation in ct scans
A146: 158 | B146: Insights into the Prevalence of Software Project Defects | C146: 2014-01-01 | D146: This paper analyses the effect of the effort distribution along the software development lifecycle on the prevalence of software defects. This analysis is based on data that was collected by the International Software Benchmarking Standards Group (ISBSG) on the development of 4,106 software projects. Data mining techniques have been applied to gain a better understanding of the behaviour of the project activities and to identify a link between the effort distribution and the prevalence of software defects. This analysis has been complemented with the use of a hierarchical clustering algorithm with a dissimilarity based on the likelihood ratio statistic, for exploratory purposes. As a result, different behaviours have been identified for this collection of software development projects, allowing for the definition of risk control strategies to diminish the number and impact of the software defects. It is expected that the use of similar estimations might greatly improve the awareness of project managers on the risks at hand. (Summary); Univ Complutense Madrid, Madrid, Spain. jpavon@fdi.ucm.es (Author of contact); This work has been done in the context of the Project ASASEC (Advisory System Against Sexual Exploitation of Children) (HOME/2010/ISEC/AG/043) supported by the European Union with the Programme Prevention and Fight against Crime. (Recognitions linked to item) | F146: Environmental Science (Miscellaneous) | G146: This paper analyses the effect of the effort distribution along the software development lifecycle on the prevalence of software defects. This analysis is based on data that was collected by the International Software Benchmarking Standards Group (ISBSG) on the development of 4,106 software projects. Data mining techniques have been applied to gain a better understanding of the behaviour of the project activities and to identify a link between the effort distribution and the prevalence of software defects. This analysis has been complemented with the use of a hierarchical clustering algorithm with a dissimilarity based on the likelihood ratio statistic, for exploratory purposes. As a result, different behaviours have been identified for this collection of software development projects, allowing for the definition of risk control strategies to diminish the number and impact of the software defects. It is expected that the use of similar estimations might greatly improve the awareness of project managers on the risks at hand. | H146: 9 | I146: 2 | J146: insights into the prevalence of software project defects
A147: 159 | B147: Nanocomposite biomaterials based on poly(ether-ether-ketone) (PEEK) and WS2 inorganic nanotubes | C147: 2014-07-28 | D147: The manuscript presents the use of tungsten disulfide inorganic nanotubes (INT-WS2) to fabricate advanced poly(ether ether ketone) (PEEK) biomaterials by a traditional melt processing technique. This strategy offers an attractive way to combine the merits of organic and inorganic materials into novel hybrid systems with improved performance. The effect of INT-WS2 content on the morphology, thermal stability, crystallization behaviour, thermal conductivity, mechanical and tribological properties is investigated in detail with various techniques. The results indicate that these inorganic nanotubes can be efficiently incorporated into the biopolymer matrix without the need for modifiers or surfactants, resulting in a very homogenous dispersion. Additionally, it is found that the increase in INT-WS2 concentration leads to changes in the crystallization behaviour without modifying the crystalline structure of PEEK in the nanocomposites. The incorporation of INT-WS2 produces higher improvements in the degradation temperature, storage modulus, thermal expansion coefficient, hardness, coefficient of friction and wear resistance of the polymer than the addition of other inorganic nanofillers or carbon nanotubes, providing an effective balance between performance, cost effectiveness and processability. These novel nanocomposites are of great interest for use in biomedical applications, particularly for orthopaedic and trauma implants. (Summary); Univ Politecn Madrid, Dept Ingn & Ciencia Mat, Escuela Tecn Super Ingn Ind, Jose Gutierrez Abascal 2, Madrid 28006, Spain. mohammed.naffakh@upm.es (Author of contact); The authors wish to thank Invibio Ltd (Lancashire, UK) for kindly providing the medical grade PEEK OPTIMA biomaterial. M. N. would also like to acknowledge the MINECO for a Ramon y Cajal' Senior Research Fellowship and Dr A. D. wishes to acknowledge the CSIC for a JAE Postdoctoral Fellowship cofinanced by the EU. Very special thanks and appreciation go to Dr Alla Zak for providing the WS2 inorganic nanotubes that made this research possible. (Recognitions linked to item) | E147: Behavior; Biopolymer nanocomposites; Composites; Cytotoxicity; Fullerene-like ws2; Mechanical-properties; Nanoparticles; Particle-size; Polymer; Tribological properties | F147: Biomedical Engineering | G147: The manuscript presents the use of tungsten disulfide inorganic nanotubes (INT-WS2) to fabricate advanced poly(ether ether ketone) (PEEK) biomaterials by a traditional melt processing technique. This strategy offers an attractive way to combine the merits of organic and inorganic materials into novel hybrid systems with improved performance. The effect of INT-WS2 content on the morphology, thermal stability, crystallization behaviour, thermal conductivity, mechanical and tribological properties is investigated in detail with various techniques. The results indicate that these inorganic nanotubes can be efficiently incorporated into the biopolymer matrix without the need for modifiers or surfactants, resulting in a very homogenous dispersion. Additionally, it is found that the increase in INT-WS2 concentration leads to changes in the crystallization behaviour without modifying the crystalline structure of PEEK in the nanocomposites. The incorporation of INT-WS2 produces higher improvements in the degradation temperature, storage modulus, thermal expansion coefficient, hardness, coefficient of friction and wear resistance of the polymer than the addition of other inorganic nanofillers or carbon nanotubes, providing an effective balance between performance, cost effectiveness and processability. These novel nanocomposites are of great interest for use in biomedical applications, particularly for orthopaedic and trauma implants. | H147: 9 | I147: 2 | J147: nanocomposite biomaterials based on polyetheretherketone peek and ws2 inorganic nanotubes
A148: 160 | B148: Development of novel melt-processable biopolymer nanocomposites based on poly(L-lactic acid) and WS2 inorganic nanotubes | C148: 2014-06-21 | D148: The use of tungsten disulphide inorganic nanotubes (INT-WS2) offers the opportunity to produce novel and advanced biopolymer-based nanocomposite materials with excellent nanoparticle dispersion without the need for modifiers or surfactants via conventional melt blending. The study of the non-isothermal melt-crystallization kinetics provides a clear picture of the transformation of poly(L-lactic acid) (PLLA) molecules from the non-ordered to the ordered state. The overall crystallization rate, final crystallinity and subsequent melting behaviour of PLLA were controlled by both the incorporation of INT-WS2 and the variation of the cooling rate. In particular, it was shown that INT-WS2 exhibits much more prominent nucleation activity on the crystallization of PLLA than other specific nucleating agents or nano-sized fillers. These features may be advantageous for the enhancement of mechanical properties and processability of PLLA-based materials. PLLA/INT-WS2 nanocomposites can be employed as low cost biodegradable materials for many eco-friendly and medical applications, and the exceptional crystallization behaviour observed opens new perspectives for scale-up and broader applications. (Summary); Univ Politecn Madrid, Dept Ingn & Ciencia Mat, Escuela Tecn Super Ingn Ind, Jose Gutierrez Abascal 2, E-28006 Madrid, Spain. mohammed.naffakh@upm.es (Author of contact); This work was supported by the Spanish Ministry Economy and Competitivity (MINECO), Project MAT-2010-21070-C02-01 and the European Commission for the X-ray synchrotron experiments performed at the Soft Condensed Matter A2 beamline at HASYLAB (DESY-Hamburg, I-20110152 EC). MN would also like to acknowledge the MINECO for a 'Ramon y Cajal' Senior Research Fellowship. Very special thanks and appreciation go to Dr. Alla Zak for providing the WS2 inorganic nanotubes that made this research possible. (Recognitions linked to item) | E148: Catalyzed nucleation; Composites; Crystal-structure; Crystallization behavior; Glass-forming melts; Kinetics; Polymers | F148: Materials Science (Miscellaneous) | G148: The use of tungsten disulphide inorganic nanotubes (INT-WS2) offers the opportunity to produce novel and advanced biopolymer-based nanocomposite materials with excellent nanoparticle dispersion without the need for modifiers or surfactants via conventional melt blending. The study of the non-isothermal melt-crystallization kinetics provides a clear picture of the transformation of poly(L-lactic acid) (PLLA) molecules from the non-ordered to the ordered state. The overall crystallization rate, final crystallinity and subsequent melting behaviour of PLLA were controlled by both the incorporation of INT-WS2 and the variation of the cooling rate. In particular, it was shown that INT-WS2 exhibits much more prominent nucleation activity on the crystallization of PLLA than other specific nucleating agents or nano-sized fillers. These features may be advantageous for the enhancement of mechanical properties and processability of PLLA-based materials. PLLA/INT-WS2 nanocomposites can be employed as low cost biodegradable materials for many eco-friendly and medical applications, and the exceptional crystallization behaviour observed opens new perspectives for scale-up and broader applications. | H148: 9 | I148: 2 | J148: development of novel meltprocessable biopolymer nanocomposites based on polyllactic acid and ws2 inorganic nanotubes
A149: 161 | B149: Evaluation of the seat fastening in the frame of a road bus submitted to frontal impact | C149: 2014-01-01 | D149: The collective intercity transportation by bus is currently a mean of locomotion much sought after by people. Security in accidents is a very important factor that must be taken into account in design of bus body structure, being the evaluation of passenger safety of this type of vehicle is an important subject that should be checked, because in many accidents occur disconnection between seats and fastening members causing serious passengers injury, often fatal. This work aims at evaluation the behavior of frame fixing of seats of intercity bus bodies, submitted to the frontal impact situation in a rigid wall of 100% offset, through evaluation by finite element method (FEM). This study uses a numerical model corresponding to the body structure and chassis, developed through flexible beam elements, combining with shell elements for the structure of the seats and its fastening members, with the objective of not missing the essential aspects of the problem, allowing the solution with a reduced computational time. The numerical model of bus body and seat was impacted against a rigid wall at a speed of 8.89 m/s, being its validation according to the deceleration curve established by Regulation 80. Then it was gotten the Von Mises stress in fastening members of the seat structure in bus body. It is also presented a proposal to improve the fastening of the seat structure, comparing the results of the stress gotten in the two types fastening submitted to the frontal impact. (Summary); Univ Passo Fundo, FEAR Coll Engn & Architecture, Passo Fundo, RS, Brazil. mwalber@upf.br (Author of contact) | E149: Bus body; Design; Fastening members; Impact; Seat | F149: Automotive Engineering | G149: The collective intercity transportation by bus is currently a mean of locomotion much sought after by people. Security in accidents is a very important factor that must be taken into account in design of bus body structure, being the evaluation of passenger safety of this type of vehicle is an important subject that should be checked, because in many accidents occur disconnection between seats and fastening members causing serious passengers injury, often fatal. This work aims at evaluation the behavior of frame fixing of seats of intercity bus bodies, submitted to the frontal impact situation in a rigid wall of 100% offset, through evaluation by finite element method (FEM). This study uses a numerical model corresponding to the body structure and chassis, developed through flexible beam elements, combining with shell elements for the structure of the seats and its fastening members, with the objective of not missing the essential aspects of the problem, allowing the solution with a reduced computational time. The numerical model of bus body and seat was impacted against a rigid wall at a speed of 8.89 m/s, being its validation according to the deceleration curve established by Regulation 80. Then it was gotten the Von Mises stress in fastening members of the seat structure in bus body. It is also presented a proposal to improve the fastening of the seat structure, comparing the results of the stress gotten in the two types fastening submitted to the frontal impact. | H149: 3 | I149: 1 | J149: evaluation of the seat fastening in the frame of a road bus submitted to frontal impact
A150: 162 | B150: Behavior, for the Lorca earthquake on 11-05-2011, of wide beam building designed without seismic considerations | C150: 2014-01-01 | D150: The recent earthquake in Lorca (11-05-2011) was the most destructive recorded event in Spain, despite its moderate magnitude. This paper describes the numerical simulation of the dynamic response to the main record of the Lorca earthquake of six 3 and 6-story buildings with one-way concrete slabs with wide beams; these buildings were designed without any seismic consideration. We have chosen this type of construction because it is potentially highly vulnerable. The six considered buildings were selected to represent a large number of buildings of this type in areas of low-to-medium seismicity (as Lorca) of Spain along the period 1974-1994. The results show that these buildings, even with the cooperation of the walls, do not have sufficient capacity to withstand the most severe component of the Lorca record. (Summary); Univ Politecn Cataluna, E-08028 Barcelona, Spain. francesc.lopez-almansa@upc.edu (Author of contact) | E150: Collapse; Lorca earthquake; Seismic vulnerability; Time history; Wide beams | F150: Architecture | G150: The recent earthquake in Lorca (11-05-2011) was the most destructive recorded event in Spain, despite its moderate magnitude. This paper describes the numerical simulation of the dynamic response to the main record of the Lorca earthquake of six 3 and 6-story buildings with one-way concrete slabs with wide beams; these buildings were designed without any seismic consideration. We have chosen this type of construction because it is potentially highly vulnerable. The six considered buildings were selected to represent a large number of buildings of this type in areas of low-to-medium seismicity (as Lorca) of Spain along the period 1974-1994. The results show that these buildings, even with the cooperation of the walls, do not have sufficient capacity to withstand the most severe component of the Lorca record. | H150: 9 | I150: 2 | J150: behavior for the lorca earthquake on 11052011 of wide beam building designed without seismic considerations
A151: 163 | B151: A remote handling rate-position controller for telemanipulating in a large workspace | C151: 2014-01-01 | D151: This paper presents a new haptic rate-position controller, which allows manipulating a slave robot in a large workspace using a small haptic device. This control algorithm is very effective when the master device is much smaller than the slave device. Haptic information is displayed to the user so as to be informed when a change in the operation mode occurs. This controller allows performing tasks in a large remote workspace by using a haptic device with a reduced workspace such as Phantom. Experimental results have been carried out using a slave robot from Kraft Telerobotics and a commercial haptic interface as a master device. A curvature path following task has been simulated using the proposed controller which was compared with the force-position control algorithm. Results obtained show that higher accuracy is obtained when the proposed method is used, spending a similar amount of time to perform the task. (C) 2013 Elsevier B.V. All rights reserved. (Summary); Ctr Automat & Robot UPM CSIC, Calle Jose Gutierrez Abacal 2, Madrid 28006, Spain. jordi.barrio@upm.es; m.ferre@upm.es; fa.suarez@upm.es; rafael.aracil@upm.es (Author of contact); This work was carried out under the EFDA Goal Oriented Training Programme (WP10-GOT-GOTRH) and the financial support of TECHNOFUSION programme from Comunidad de Madrid, which are greatly acknowledged. The views and opinions expressed herein do not necessarily reflect those of the European Commission. (Recognitions linked to item) | E151: Haptic interfaces; Performance; Remote handling; Telemanipulation | F151: Civil and Structural Engineering | G151: This paper presents a new haptic rate-position controller, which allows manipulating a slave robot in a large workspace using a small haptic device. This control algorithm is very effective when the master device is much smaller than the slave device. Haptic information is displayed to the user so as to be informed when a change in the operation mode occurs. This controller allows performing tasks in a large remote workspace by using a haptic device with a reduced workspace such as Phantom. Experimental results have been carried out using a slave robot from Kraft Telerobotics and a commercial haptic interface as a master device. A curvature path following task has been simulated using the proposed controller which was compared with the force-position control algorithm. Results obtained show that higher accuracy is obtained when the proposed method is used, spending a similar amount of time to perform the task. | H151: 9 | I151: 2 | J151: a remote handling rateposition controller for telemanipulating in a large workspace
A152: 164 | B152: Code assessment and modelling for Design Basis Accident Analysis of the European sodium fast reactor design. Part I: System description, modelling and benchmarking | C152: 2014-01-01 | D152: The new reactor concepts proposed in the Generation IV International Forum (GIF) are conceived to improve the use of natural resources, reduce the amount of high-level radioactive waste and excel in their reliability and safe operation. Among these novel designs sodium fast reactors (SFRs) stand out due to their technological feasibility as demonstrated in several countries during the last decades. As part of the contribution of EURATOM to GIF the CP-ESFR is a collaborative project with the objective, among others, to perform extensive analysis on safety issues involving renewed SFR demonstrator designs. The verification of computational tools able to simulate the plant behaviour under postulated accidental conditions by code-to-code comparison was identified as a key point to ensure reactor safety. In this line, several organizations employed coupled neutronic and thermal-hydraulic system codes able to simulate complex and specific phenomena involving multi-physics studies adapted to this particular fast reactor technology. In the Introduction of this paper the framework of this study is discussed, the second section describes the envisaged plant design and the commonly agreed upon modelling guidelines. The third section presents a comparative analysis of the calculations performed by each organisation applying their models and codes to a common agreed transient with the objective to harmonize the models as well as validating the implementation of all relevant physical phenomena in the different system codes. (C) 2013 Elsevier B.V. All rights reserved. (Summary); JRC IET European Commiss, Westerduinweg 3,POB 2, NL-1755 ZG Petten, Netherlands. aurelio.lazaro-chueca@ec.europa.eu (Author of contact); We would like to acknowledge the financial support given to the project by the European Commission through the Seventh Framework Programme (FP7). (Recognitions linked to item) | E152: Behavior; Fuel | F152: Safety, Risk, Reliability and Quality | G152: The new reactor concepts proposed in the Generation IV International Forum (GIF) are conceived to improve the use of natural resources, reduce the amount of high-level radioactive waste and excel in their reliability and safe operation. Among these novel designs sodium fast reactors (SFRs) stand out due to their technological feasibility as demonstrated in several countries during the last decades. As part of the contribution of EURATOM to GIF the CP-ESFR is a collaborative project with the objective, among others, to perform extensive analysis on safety issues involving renewed SFR demonstrator designs. The verification of computational tools able to simulate the plant behaviour under postulated accidental conditions by code-to-code comparison was identified as a key point to ensure reactor safety. In this line, several organizations employed coupled neutronic and thermal-hydraulic system codes able to simulate complex and specific phenomena involving multi-physics studies adapted to this particular fast reactor technology. In the Introduction of this paper the framework of this study is discussed, the second section describes the envisaged plant design and the commonly agreed upon modelling guidelines. The third section presents a comparative analysis of the calculations performed by each organisation applying their models and codes to a common agreed transient with the objective to harmonize the models as well as validating the implementation of all relevant physical phenomena in the different system codes. | H152: 7 | I152: 2 | J152: code assessment and modelling for design basis accident analysis of the european sodium fast reactor design part i system description modelling and benchmarking
A153: 165 | B153: Effect of Temperature on the Evolution of Colour during the Maceration of Fruits in Liquor | C153: 2014-01-01 | D153: The effect of temperature on the kinetics of pigment extraction during the maceration of different fruits (raspberry, blackberry, and cranberry) into a commercially available hard spirit (orujo, with 42% v/v ethanol) was evaluated. The analytical method used was UV-Vis spectrophotometry. The initial extraction rate showed an Arrhenius-type dependence with apparent energy activation of 28.8, 69.8, and 55.6 kJ/mol, respectively. Furthermore, a study about the evolution of the colour (from colourless to reddish colour appearance) during the soaking process was done by calculating the CIE tristimulus values (X, Y, Z) for illuminant C, until reaching the apparent stabilisation of colour, which occurs after about two to four weeks for the studied temperatures (5, 23, and 40 C). Studies about the evolution of colour in the soaking process of this kind of fruit liquors can lead to a better understanding of this process, and thus to a better control over the mechanisms underlying it. (Summary); Univ Politecn Madrid, Dept Ingn Quim Ind & Medio Ambiente, ETSI Ind, Jose Gutierrez Abascal 2, E-28006 Madrid, Spain. gabriel.pinto@upm.es (Author of contact); Supported by the Universidad Politecnica de Madrid, Project No. PT 12_13-01001. (Recognitions linked to item) | E153: Acetaldehyde; Anthocyanins; Ethanol; Extraction; Juice; Kinetics; Ph; Pigment; Red wines; Spectral method; Spirit | F153: Food Science | G153: The effect of temperature on the kinetics of pigment extraction during the maceration of different fruits (raspberry, blackberry, and cranberry) into a commercially available hard spirit (orujo, with 42% v/v ethanol) was evaluated. The analytical method used was UV-Vis spectrophotometry. The initial extraction rate showed an Arrhenius-type dependence with apparent energy activation of 28.8, 69.8, and 55.6 kJ/mol, respectively. Furthermore, a study about the evolution of the colour (from colourless to reddish colour appearance) during the soaking process was done by calculating the CIE tristimulus values (X, Y, Z) for illuminant C, until reaching the apparent stabilisation of colour, which occurs after about two to four weeks for the studied temperatures (5, 23, and 40 C). Studies about the evolution of colour in the soaking process of this kind of fruit liquors can lead to a better understanding of this process, and thus to a better control over the mechanisms underlying it. | H153: 9 | I153: 2 | J153: effect of temperature on the evolution of colour during the maceration of fruits in liquor
A154: 166 | B154: Viability of the ESS-Bilbao neutron source for irradiation of nuclear fusion materials | C154: 2014-01-01 | D154: The ESS-Bilbao neutron source, currently under construction, is conceived as a multipurpose facility. It will offer a fast neutron beam line for materials irradiation. In this paper we discuss the viability of ESS-Bilbao for experimental studies of fusion materials. Making use of the already designed target station we have calculated the neutron spectrum expected in the fast neutron line. Then, we have studied the neutron irradiation effects in two model materials: iron and silica. We have calculated the expected PICA (primary knock-on atom) spectra and light species production as well as the damage production in these materials. Regarding structural materials, we conclude that the ESS-Bilbao neutron irradiation facility will play a minor role due to the resulting low neutron fluxes (about two orders of magnitude lower than in fusion reactors). On the other hand, ESS-Bilbao turns out to be relevant for studies of final lenses in laser fusion power plants. A comparison with the conditions expected for HiPER final lenses shows that the fluxes will be only a factor 5 smaller in ESS-Bilbao and the PICA spectra will be very similar. Taking into account, in addition, that relevant effects on lenses occur from the onset of irradiation, we conclude that an appropriate irradiation cell with in situ characterisation techniques will make ESS-Bilbao very attractive for applied neutron damage studies of laser fusion final lenses. Finally, we compare ESS-Bilbao with other facilities. (C) 2013 Elsevier B.V. All rights reserved. (Summary); Inst Fus Nucl UPM, Jose Gutierrez Abascal 2, E-28006 Madrid, Spain. angel.rodriguez.paramo@upm.es (Author of contact); This work has been possible thanks the Spanish MINECO for financial support through the projects ENE-2012-39787-C06-03 and AIC-A-2011-0718, the computing infrastructure of the i2BAS-QUE academic network and to the PIF program of the Universidad Politecnica de Madrid. (Recognitions linked to item) | E154: Absorption; Displacement damage; Fused-silica; Iron; Metals; Radiation; Spallation | F154: Nuclear Energy and Engineering | G154: The ESS-Bilbao neutron source, currently under construction, is conceived as a multipurpose facility. It will offer a fast neutron beam line for materials irradiation. In this paper we discuss the viability of ESS-Bilbao for experimental studies of fusion materials. Making use of the already designed target station we have calculated the neutron spectrum expected in the fast neutron line. Then, we have studied the neutron irradiation effects in two model materials: iron and silica. We have calculated the expected PICA (primary knock-on atom) spectra and light species production as well as the damage production in these materials. Regarding structural materials, we conclude that the ESS-Bilbao neutron irradiation facility will play a minor role due to the resulting low neutron fluxes (about two orders of magnitude lower than in fusion reactors). On the other hand, ESS-Bilbao turns out to be relevant for studies of final lenses in laser fusion power plants. A comparison with the conditions expected for HiPER final lenses shows that the fluxes will be only a factor 5 smaller in ESS-Bilbao and the PICA spectra will be very similar. Taking into account, in addition, that relevant effects on lenses occur from the onset of irradiation, we conclude that an appropriate irradiation cell with in situ characterisation techniques will make ESS-Bilbao very attractive for applied neutron damage studies of laser fusion final lenses. Finally, we compare ESS-Bilbao with other facilities. | H154: 7 | I154: 2 | J154: viability of the essbilbao neutron source for irradiation of nuclear fusion materials
A155: 167 | B155: Health monitoring of web plastifying dampers subjected to cyclic loading through vibration tests | C155: 2014-01-01 | D155: This article investigates experimentally the application of health monitoring techniques to assess the damage on a particular kind of hysteretic (metallic) damper called web plastifying dampers, which are subjected to cyclic loading. In general terms, hysteretic dampers are increasingly used as passive control systems in advanced earthquake-resistant structures. Nonparametric statistical processing of the signals obtained from simple vibration tests of the web plastifying damper is used here to propose an area index damage. This area index damage is compared with an alternative energy-based index of damage proposed in past research that is based on the decomposition of the load-displacement curve experienced by the damper. Index of damage has been proven to accurately predict the level of damage and the proximity to failure of web plastifying damper, but obtaining the load-displacement curve for its direct calculation requires the use of costly instrumentation. For this reason, the aim of this study is to estimate index of damage indirectly from simple vibration tests, calling for much simpler and cheaper instrumentation, through an auxiliary index called area index damage. Web plastifying damper is a particular type of hysteretic damper that uses the out-of-plane plastic deformation of the web of I-section steel segments as a source of energy dissipation. Four I-section steel segments with similar geometry were subjected to the same pattern of cyclic loading, and the damage was evaluated with the index of damage and area index damage indexes at several stages of the loading process. A good correlation was found between area index damage and index of damage. Based on this correlation, simple formulae are proposed to estimate index of damage from the area index damage. (Summary); Univ Granada, Dept Appl Phys, E-18071 Granada, Spain. lyrome@ugr.es (Author of contact); This research received the financial support of the local government of Spain, Consejeria de Innovacion, Ciencia y Tecnologia, Projects P07-TEP-02610 and P08-TEP-03641. (Recognitions linked to item) | E155: Crack detection; Damage detection; Earthquake excitation; Energy-based damage index; Energy-dissipation; Frequency; Health monitoring; Hysteretic dampers; Identification; Mass dampers; Neural-networks; Piezoceramic sensor; Sensor network; Structural damage; Vibration tests | F155: Mechanical Engineering | G155: This article investigates experimentally the application of health monitoring techniques to assess the damage on a particular kind of hysteretic (metallic) damper called web plastifying dampers, which are subjected to cyclic loading. In general terms, hysteretic dampers are increasingly used as passive control systems in advanced earthquake-resistant structures. Nonparametric statistical processing of the signals obtained from simple vibration tests of the web plastifying damper is used here to propose an area index damage. This area index damage is compared with an alternative energy-based index of damage proposed in past research that is based on the decomposition of the load-displacement curve experienced by the damper. Index of damage has been proven to accurately predict the level of damage and the proximity to failure of web plastifying damper, but obtaining the load-displacement curve for its direct calculation requires the use of costly instrumentation. For this reason, the aim of this study is to estimate index of damage indirectly from simple vibration tests, calling for much simpler and cheaper instrumentation, through an auxiliary index called area index damage. Web plastifying damper is a particular type of hysteretic damper that uses the out-of-plane plastic deformation of the web of I-section steel segments as a source of energy dissipation. Four I-section steel segments with similar geometry were subjected to the same pattern of cyclic loading, and the damage was evaluated with the index of damage and area index damage indexes at several stages of the loading process. A good correlation was found between area index damage and index of damage. Based on this correlation, simple formulae are proposed to estimate index of damage from the area index damage. | H155: 9 | I155: 2 | J155: health monitoring of web plastifying dampers subjected to cyclic loading through vibration tests
A156: 168 | B156: Uncertainty in ellipse fitting using a flatbed scanner: development and experimental verification | C156: 2014-01-01 | D156: In the field of dimensional metrology, the use of optical measuring machines requires the handling of a large number of measurement points, or scanning points, taken from the image of the measurand. The presence of correlation between these measurement points has a significant influence on the uncertainty of the result. The aim of this work is the development of an estimation procedure for the uncertainty of measurement in a geometrically elliptical shape, taking into account the correlation between the scanning points. These points are obtained from an image produced using a commercial flat bed scanner. The characteristic parameters of the ellipse (coordinates of the center, semi-axes and the angle of the semi-major axis with regard to the horizontal) are determined using a least squares fit and orthogonal distance regression. The uncertainty is estimated using the information from the auto-correlation function of the residuals and is propagated through the fitting algorithm according to the rules described in Evaluation of Measurement Data-Supplement 2 to the 'Guide to the Expression of Uncertainty in Measurement'-Extension to any number of output quantities. By introducing the concept of cut-off length, it can be observed how it is possible to take into account the presence of the correlation in the estimation of uncertainty in a very simple way while avoiding underestimation. (Summary); Univ Politecn Madrid, Dept Fis Aplicada Ingn Ind, C Jose Gutierrez Abascal 2, E-28006 Madrid, Spain. jvo@etsii.upm.es; amsanchez@etsii.upm.es; m.berzal@upm.es; piera.maresca@upm.es; emilio.gomez@upm.es (Author of contact); This work has been carried out within the DPI2008-01351 project, financed by the Spanish Government's National Industrial Design and Innovation Plan (Plan Nacional de Diseno e Innovacion Industrial). (Recognitions linked to item) | E156: Correlation; Cut-off length; Flatbed scanner; Image-analysis; Least square method; Measurement uncertainty; Optical dimensional metrology; Orthogonal distance | F156: Engineering (Miscellaneous) | G156: In the field of dimensional metrology, the use of optical measuring machines requires the handling of a large number of measurement points, or scanning points, taken from the image of the measurand. The presence of correlation between these measurement points has a significant influence on the uncertainty of the result. The aim of this work is the development of an estimation procedure for the uncertainty of measurement in a geometrically elliptical shape, taking into account the correlation between the scanning points. These points are obtained from an image produced using a commercial flat bed scanner. The characteristic parameters of the ellipse (coordinates of the center, semi-axes and the angle of the semi-major axis with regard to the horizontal) are determined using a least squares fit and orthogonal distance regression. The uncertainty is estimated using the information from the auto-correlation function of the residuals and is propagated through the fitting algorithm according to the rules described in Evaluation of Measurement Data-Supplement 2 to the 'Guide to the Expression of Uncertainty in Measurement'-Extension to any number of output quantities. By introducing the concept of cut-off length, it can be observed how it is possible to take into account the presence of the correlation in the estimation of uncertainty in a very simple way while avoiding underestimation. | H156: 9 | I156: 2 | J156: uncertainty in ellipse fitting using a flatbed scanner development and experimental verification
A157: 169 | B157: Emission inventories and modeling requirements for the development of air quality plans. Application to Madrid (Spain) | C157: 2014-01-01 | D157: Modeling is an essential tool for the development of atmospheric emission abatement measures and air quality plans. Most often these plans are related to urban environments with high emission density and population exposure. However, air quality modeling in urban areas is a rather challenging task. As environmental standards become more stringent (e.g. European Directive 2008/50/EC), more reliable and sophisticated modeling tools are needed to simulate measures and plans that may effectively tackle air quality exceedances, common in large urban areas across Europe, particularly for NO2. This also implies that emission inventories must satisfy a number of conditions such as consistency across the spatial scales involved in the analysis, consistency with the emission inventories used for regulatory purposes and versatility to match the requirements of different air quality and emission projection models. This study reports the modeling activities carried out in Madrid (Spain) highlighting the atmospheric emission inventory development and preparation as an illustrative example of the combination of models and data needed to develop a consistent air quality plan at urban level. These included a series of source apportionment studies to define contributions from the international, national, regional and local sources in order to understand to what extent local authorities can enforce meaningful abatement measures. Moreover, source apportionment studies were conducted in order to define contributions from different sectors and to understand the maximum feasible air quality improvement that can be achieved by reducing emissions from those sectors, thus targeting emission reduction policies to the most relevant activities. Finally, an emission scenario reflecting the effect of such policies was developed and the associated air quality was modeled. (C) 2013 Elsevier B.V. All rights reserved. (Summary); Tech Univ Madrid UPM, Dept Chem & Environm Engn, Environm Modelling Lab, C Jose Gutierrez Abascal 2, Madrid 28006, Spain. rborge@etsii.upm.es (Author of contact); The Madrid City Council provided the traffic model and supported this study. The CMAQ modeling system was made available by the US EPA and it is supported by the Community Modeling and Analysis System (CMAS) Center. The authors also acknowledge the use of emission datasets and monitoring data from the Spanish and Portuguese Ministries of Environment. (Recognitions linked to item) | E157: emission inventory; madrid; modeling; no(2); smoke; City; Emission inventory; High-resolution; Madrid; Modeling; Nitrogen-dioxide; No 2; No2; Pollution; Sensitivity-analysis; Simulations; Smoke; Source apportionment; Traffic emissions; Uk; Urban air quality; Variability | F157: Environmental Engineering | G157: Modeling is an essential tool for the development of atmospheric emission abatement measures and air quality plans. Most often these plans are related to urban environments with high emission density and population exposure. However, air quality modeling in urban areas is a rather challenging task. As environmental standards become more stringent (e.g. European Directive 2008/50/EC), more reliable and sophisticated modeling tools are needed to simulate measures and plans that may effectively tackle air quality exceedances, common in large urban areas across Europe, particularly for NO2. This also implies that emission inventories must satisfy a number of conditions such as consistency across the spatial scales involved in the analysis, consistency with the emission inventories used for regulatory purposes and versatility to match the requirements of different air quality and emission projection models. This study reports the modeling activities carried out in Madrid (Spain) highlighting the atmospheric emission inventory development and preparation as an illustrative example of the combination of models and data needed to develop a consistent air quality plan at urban level. These included a series of source apportionment studies to define contributions from the international, national, regional and local sources in order to understand to what extent local authorities can enforce meaningful abatement measures. Moreover, source apportionment studies were conducted in order to define contributions from different sectors and to understand the maximum feasible air quality improvement that can be achieved by reducing emissions from those sectors, thus targeting emission reduction policies to the most relevant activities. Finally, an emission scenario reflecting the effect of such policies was developed and the associated air quality was modeled. | H157: 11 | I157: 1 | J157: emission inventories and modeling requirements for the development of air quality plans application to madrid spain
A158: 170 | B158: Detection and Tracking of Dynamic Objects by Using a Multirobot System: Application to Critical Infrastructures Surveillance | C158: 2014-02-12 | D158: The detection and tracking of mobile objects (DATMO) is progressively gaining importance for security and surveillance applications. This article proposes a set of new algorithms and procedures for detecting and tracking mobile objects by robots that work collaboratively as part of a multirobot system. These surveillance algorithms are conceived of to work with data provided by long distance range sensors and are intended for highly reliable object detection in wide outdoor environments. Contrary to most common approaches, in which detection and tracking are done by an integrated procedure, the approach proposed here relies on a modular structure, in which detection and tracking are carried out independently, and the latter might accept input data from different detection algorithms. Two movement detection algorithms have been developed for the detection of dynamic objects by using both static and/or mobile robots. The solution to the overall problem is based on the use of a Kalman filter to predict the next state of each tracked object. Additionally, new tracking algorithms capable of combining dynamic objects lists coming from either one or various sources complete the solution. The complementary performance of the separated modular structure for detection and identification is evaluated and, finally, a selection of test examples discussed. (Summary); Univ Politecn Madrid, Robot & Cybernet Res Grp, Ctr Automat & Robot, CSIC, C Jose Gutierrez Abascal 2, E-28006 Madrid, Spain. gonzalo.rcanosa@upm.es; j.cerro@upm.es; antonio.barrientos@upm.es (Author of contact); This work was supported by the Robotics and Cybernetics Group at Universidad Politcnica de Madrid (Spain) and funded under the projects: ROTOS: Multi-robot system for outdoor infrastructures protection, sponsored by the Spanish Ministry of Education and Science (DPI2010-17998), and ROBOCITY2030, sponsored by the Community of Madrid (S-0505/DPI/000235). (Recognitions linked to item) | E158: Camera; Critical infrastructure surveillance; Datmo; Information; Laser scanner; Moving-objects; Multirobot; Robot; Vehicle detection | F158: Electrical and Electronic Engineering | G158: The detection and tracking of mobile objects (DATMO) is progressively gaining importance for security and surveillance applications. This article proposes a set of new algorithms and procedures for detecting and tracking mobile objects by robots that work collaboratively as part of a multirobot system. These surveillance algorithms are conceived of to work with data provided by long distance range sensors and are intended for highly reliable object detection in wide outdoor environments. Contrary to most common approaches, in which detection and tracking are done by an integrated procedure, the approach proposed here relies on a modular structure, in which detection and tracking are carried out independently, and the latter might accept input data from different detection algorithms. Two movement detection algorithms have been developed for the detection of dynamic objects by using both static and/or mobile robots. The solution to the overall problem is based on the use of a Kalman filter to predict the next state of each tracked object. Additionally, new tracking algorithms capable of combining dynamic objects lists coming from either one or various sources complete the solution. The complementary performance of the separated modular structure for detection and identification is evaluated and, finally, a selection of test examples discussed. | H158: 9 | I158: 2 | J158: detection and tracking of dynamic objects by using a multirobot system application to critical infrastructures surveillance
... A167: 179 | B167: Analysis of Pu-238 and Fe-56 Evaluated Data for Use in MYRRHA | C167: 2014-01-01 | D167: A sensitivity analysis on the multiplication factor, k(eff), to the cross section data has been carried out for the MYRRHA critical configuration in order to show the most relevant reactions. With these results, a further analysis on the Pu-238 and Fe-56 cross sections has been performed, comparing the evaluations provided in the JEFF-3.1.2 and ENDF/B-VII.1 libraries for these nuclides. Then, the effect in MYRRHA of the differences between evaluations are analysed, presenting the source of the differences. With these results, recommendations for the Fe-56 and Pu-238 evaluations are suggested. These calculations have been performed with SCALE6.1 and MCNPX-2.7e. (Summary); Univ Politecn Madrid, Dpto Ingn Nucl, E-28006 Madrid, Spain. cj.diez@upm.es (Author of contact); The first author would like to thank SCK center dot CEN and EC-JRC-IRMM for hosting him during his internship in 2012. The research leading to these results has received funding from FP7-EURATOM-FISSION-2009: Project ANDES/249671. Also, this work is partially supported by Ministry of Education of Spain with a FPU grant (AP2009-1801) for the first author. (Recognitions linked to item) | E167: Library; Nuclear-data; Science | F167: Nuclear and High Energy Physics | G167: A sensitivity analysis on the multiplication factor, k(eff), to the cross section data has been carried out for the MYRRHA critical configuration in order to show the most relevant reactions. With these results, a further analysis on the Pu-238 and Fe-56 cross sections has been performed, comparing the evaluations provided in the JEFF-3.1.2 and ENDF/B-VII.1 libraries for these nuclides. Then, the effect in MYRRHA of the differences between evaluations are analysed, presenting the source of the differences. With these results, recommendations for the Fe-56 and Pu-238 evaluations are suggested. These calculations have been performed with SCALE6.1 and MCNPX-2.7e. | H167: 7 | I167: 2 | J167: analysis of pu238 and fe56 evaluated data for use in myrrha
A168: 180 | B168: Nuclear Data Uncertainty Propagation to Reactivity Coefficients of a Sodium Fast Reactor | C168: 2014-01-01 | D168: The assessment of the uncertainty levels on the design and safety parameters for the innovative European Sodium Fast Reactor (ESFR) is mandatory. Some of these relevant safety quantities are the Doppler and void reactivity coefficients, whose uncertainties are quantified. Besides, the nuclear reaction data where an improvement will certainly benefit the design accuracy are identified. This work has been performed with the SCALE 6.1 codes suite and its multigroups cross sections library based on ENDF/B-VII.0 evaluation. (Summary); Univ Politecn Madrid, Dept Ingn Nucl, Calle Jose Gutierrez Abascal 2, E-28006 Madrid, Spain. josejavier.herrero@upm.es (Author of contact); The research leading to these results has received funding from the European Atomic Energy Community's 7th Framework Program in the ANDES project under grant agreement No. 249671. It has also been partially funded by the specific collaborative agreement between CIEMAT and UNED/UPM in the area of High level waste transmutation. The core specifications used for this analysis come from the ESFR Collaborative Project, from the European Community's Seventh Framework Program [FP7/2007-2013]. (Recognitions linked to item) | F168: Nuclear and High Energy Physics | G168: The assessment of the uncertainty levels on the design and safety parameters for the innovative European Sodium Fast Reactor (ESFR) is mandatory. Some of these relevant safety quantities are the Doppler and void reactivity coefficients, whose uncertainties are quantified. Besides, the nuclear reaction data where an improvement will certainly benefit the design accuracy are identified. This work has been performed with the SCALE 6.1 codes suite and its multigroups cross sections library based on ENDF/B-VII.0 evaluation. | H168: 7 | I168: 2 | J168: nuclear data uncertainty propagation to reactivity coefficients of a sodium fast reactor
A169: 181 | B169: Propagation of Neutron Cross Section, Fission Yield, and Decay Data Uncertainties in Depletion Calculations | C169: 2014-01-01 | D169: Propagation of nuclear data uncertainties in reactor calculations is interesting for design purposes and libraries evaluation. Previous versions of the GRS XSUSA library propagated only neutron cross section uncertainties. We have extended XSUSA uncertainty assessment capabilities by including propagation of fission yields and decay data uncertainties due to the their relevance in depletion simulations. We apply this extended methodology to the UAM6 PWR Pin-Cell Burnup Benchmark, which involves uncertainty propagation through burnup. (Summary); Univ Politecn Madrid, Dept Nucl Engn, C Jose Gutierrez Abascal 2, Madrid 28006, Spain. jesus.salvador.martinez.gonzalez@gmail.com (Author of contact); J.S.M. wishes to thank the Spanish Nuclear Safety Council, Jose Manuel Conde and Consuelo Alejano. This work is supported by the German Federal Ministry of Economics and Technology, and it is performed in the framework of the agreement in the area of Burn-up Credit and Uncertainty Propagation in Criticality Safety between the Spanish Nuclear Safety Council (CSN) and the Universidad Politecnica de Madrid. (Recognitions linked to item) | F169: Nuclear and High Energy Physics | G169: Propagation of nuclear data uncertainties in reactor calculations is interesting for design purposes and libraries evaluation. Previous versions of the GRS XSUSA library propagated only neutron cross section uncertainties. We have extended XSUSA uncertainty assessment capabilities by including propagation of fission yields and decay data uncertainties due to the their relevance in depletion simulations. We apply this extended methodology to the UAM6 PWR Pin-Cell Burnup Benchmark, which involves uncertainty propagation through burnup. | H169: 7 | I169: 2 | J169: propagation of neutron cross section fission yield and decay data uncertainties in depletion calculations
A170: 182 | B170: Testing JEFF-3.1.1 and ENDF/B-VII.1 Decay and Fission Yield Nuclear Data Libraries with Fission Pulse Neutron Emission and Decay Heat Experiments | C170: 2014-01-01 | D170: The aim of this work is to test the present status of Evaluated Nuclear Decay and Fission Yield Data Libraries to predict decay heat and delayed neutron emission rate, average neutron energy and neutron delayed spectra after a neutron fission pulse. Calculations are performed with JEFF-3.1.1 and ENDF/B-VII.1, and these are compared with experimental values. An uncertainty propagation assessment of the current nuclear data uncertainties is performed. (Summary); Univ Politecn Madrid, Dept Ingn Nucl, Madrid, Spain. oscar.cabellos@upm.es (Author of contact); This research has received funding from the European Atomic Energy Community's 7th Framework Programme in the ANDES project under Grant No. 249671, and from the specific collaborative agreement between CIEMAT and UNED/UPM in the area of High level waste transmutation. (Recognitions linked to item) | E170: Products; Pu-239; U-233 | F170: Nuclear and High Energy Physics | G170: The aim of this work is to test the present status of Evaluated Nuclear Decay and Fission Yield Data Libraries to predict decay heat and delayed neutron emission rate, average neutron energy and neutron delayed spectra after a neutron fission pulse. Calculations are performed with JEFF-3.1.1 and ENDF/B-VII.1, and these are compared with experimental values. An uncertainty propagation assessment of the current nuclear data uncertainties is performed. | H170: 7 | I170: 2 | J170: testing jeff311 and endfbvii1 decay and fission yield nuclear data libraries with fission pulse neutron emission and decay heat experiments
A171: 183 | B171: Study of PM10 and PM2.5 levels in three European cities: Analysis of intra and inter urban variations | C171: 2014-04-01 | D171: In the present paper, 1-year PM10 and PM2.5 data from roadside and urban background monitoring stations in Athens (Greece), Madrid (Spain) and London (UK) are analysed in relation to other air pollutants (NO, NO2, NOx, CO, O-3 and SO2) and several meteorological parameters (wind velocity, temperature, relative humidity, precipitation, solar radiation and atmospheric pressure), in order to investigate the sources and factors affecting particulate pollution in large European cities. Principal component and regression analyses are therefore used to quantify the contribution of both combustion and non-combustion sources to the PM10 and PM2.5 levels observed. The analysis reveals that the EU legislated PM10 and PM2.5 limit values are frequently breached, forming a potential public health hazard in the areas studied. The seasonal variability patterns of particulates varies among cities and sites, with Athens and Madrid presenting higher PM10 concentrations during the warm period and suggesting the larger relative contribution of secondary and natural particles during hot and dry days. It is estimated that the contribution of non-combustion sources varies substantially among cities, sites and seasons and ranges between 38-67% and 40-62% in London, 26-50% and 20-62% in Athens, and 31-58% and 33-68% in Madrid, for both PM10 and PM2.5. Higher contributions from non-combustion sources are found at urban background sites in all three cities, whereas in the traffic sites the seasonal differences are smaller. In addition, the non-combustion fraction of both particle metrics is higher during the warm season at all sites. On the whole, the analysis provides evidence of the substantial impact of non-combustion sources on local air quality in all three cities. While vehicular exhaust emissions carry a large part of the risk posed on human health by particle exposure, it is most likely that mitigation measures designed for their reduction will have a major effect only at traffic sites and additional measures will be necessary for the control of background levels. However, efforts in mitigation strategies should always focus on optimal health effects. (C) 2014 Elsevier Ltd. All rights reserved. (Summary); Univ Ioannina, Dept Phys, Lab Meteorol, GR-45110 Ioannina, Greece. apaschal@cc.uoi.gr (Author of contact) | E171: Aerosol; Air quality; Athens; Fine; Madrid spain; Mass; Matter; Metropolitan-area; Non-combustion sources; Particulate air-pollution; Particulate matter; Seasonal variability; Size distribution; Temporal variations; Traffic emissions; Urban background | F171: Environmental Science (Miscellaneous) | G171: In the present paper, 1-year PM10 and PM2.5 data from roadside and urban background monitoring stations in Athens (Greece), Madrid (Spain) and London (UK) are analysed in relation to other air pollutants (NO, NO2, NOx, CO, O-3 and SO2) and several meteorological parameters (wind velocity, temperature, relative humidity, precipitation, solar radiation and atmospheric pressure), in order to investigate the sources and factors affecting particulate pollution in large European cities. Principal component and regression analyses are therefore used to quantify the contribution of both combustion and non-combustion sources to the PM10 and PM2.5 levels observed. The analysis reveals that the EU legislated PM10 and PM2.5 limit values are frequently breached, forming a potential public health hazard in the areas studied. The seasonal variability patterns of particulates varies among cities and sites, with Athens and Madrid presenting higher PM10 concentrations during the warm period and suggesting the larger relative contribution of secondary and natural particles during hot and dry days. It is estimated that the contribution of non-combustion sources varies substantially among cities, sites and seasons and ranges between 38-67% and 40-62% in London, 26-50% and 20-62% in Athens, and 31-58% and 33-68% in Madrid, for both PM10 and PM2.5. Higher contributions from non-combustion sources are found at urban background sites in all three cities, whereas in the traffic sites the seasonal differences are smaller. In addition, the non-combustion fraction of both particle metrics is higher during the warm season at all sites. On the whole, the analysis provides evidence of the substantial impact of non-combustion sources on local air quality in all three cities. While vehicular exhaust emissions carry a large part of the risk posed on human health by particle exposure, it is most likely that mitigation measures designed for their reduction will have a major effect only at traffic sites and additional measures will be necessary for the control of background levels. However, efforts in mitigation strategies should always focus on optimal health effects. | H171: 11 | I171: 1 | J171: study of pm10 and pm25 levels in three european cities analysis of intra and inter urban variations
A172: 184 | B172: A real time rescheduling algorithm based in Lyapunov stability's index for metro lines | C172: 2014-01-01 | D172: A new Lyapunov-based index for designing a rescheduling algorithm in real time for metro lines has been proposed in this paper. A modified real time discrete space state model which considers saturation effects in the metro line has been utilized in this study. Once the space state model has been obtained, the direct method of Lyapunov is applied in order to analyze the stability of the metro line system. As a result of this analysis not only a new stability index is proposed, but also the establishment of three stability zones to indicate the current state of the system. Finally, a new algorithm which allows the rescheduling of the timetable in the real time of the trains under presence of medium disturbances has been presented. (Summary); Univ Tecnol Panama, Fac Ingn Elect, Ave Univ Tecnol Panama, Panama City, Panama. aranzazu.berbey@utp.ac.pa; Ramon.galan@upm.es; pablo.sansegundo@upm.es; juandedios.sanz@upm.es; rony.caballero@utp.ac.pa (Author of contact) | E172: Lyapunov stability; Metro system; Real time planning; Traffic regulation | F172: Control and Systems Engineering | G172: A new Lyapunov-based index for designing a rescheduling algorithm in real time for metro lines has been proposed in this paper. A modified real time discrete space state model which considers saturation effects in the metro line has been utilized in this study. Once the space state model has been obtained, the direct method of Lyapunov is applied in order to analyze the stability of the metro line system. As a result of this analysis not only a new stability index is proposed, but also the establishment of three stability zones to indicate the current state of the system. Finally, a new algorithm which allows the rescheduling of the timetable in the real time of the trains under presence of medium disturbances has been presented. | H172: 11 | I172: 1 | J172: a real time rescheduling algorithm based in lyapunov stabilitys index for metro lines
A173: 185 | B173: Road Dust Emission Sources and Assessment of Street Washing Effect | C173: 2014-04-01 | D173: Although previous studies report on the effect of street washing on ambient particulate matter levels, there is a lack of studies investigating the results of street washing on the emission strength of road dust. A sampling campaign was conducted in Madrid urban area during July 2009 where road dust samples were collected in two sites, namely Reference site (where the road surface was not washed) and Pelayo site (where street washing was performed daily during night). Following the chemical characterization of the road dust particles the emission sources were resolved by means of Positive Matrix Factorization, PMF (Multilinear Engine scripting) and the mass contribution of each source was calculated for the two sites. Mineral dust, brake wear, tire wear, carbonaceous emissions and construction dust were the main sources of road dust with mineral and construction dust being the major contributors to inhalable road dust load. To evaluate the effectiveness of street washing on the emission sources, the sources mass contributions between the two sites were compared. Although brake wear and tire wear had lower concentrations at the site where street washing was performed, these mass differences were not statistically significant and the temporal variation did not show the expected build-up after dust removal. It was concluded that the washing activities resulted merely in a road dust moistening, without effective removal and that mobilization of particles took place in a few hours between washing and sampling. The results also indicated that it is worth paying attention to the dust dispersed from the construction sites as they affect the emission strength in nearby streets. (Summary); Inst Environm Assessment & Water Res IDAEA CSIC, Barcelona, Spain. angeliki.karanasiou@idaea.csic.es (Author of contact); The authors wish to thank the City Council of Madrid for modifying their street washing activities during the campaign. We also thank Jorge Pey and Cristina Reche for their help during the collection of the road dust samples. This project was financed by the Spanish Ministry of the Environment and Rural and Marine Affairs (SERCA-058/PC08/3-18.1). (Recognitions linked to item) | E173: Aerosol; Chemical-composition; Cities; Environment; Fine; Fugitive dust; Madrid; Non-exhaust emissions; Particles; Particulate matter; Pm10; Pm2.5; Resuspension; Road dust; Source apportionment; Spain | F173: Pollution | G173: Although previous studies report on the effect of street washing on ambient particulate matter levels, there is a lack of studies investigating the results of street washing on the emission strength of road dust. A sampling campaign was conducted in Madrid urban area during July 2009 where road dust samples were collected in two sites, namely Reference site (where the road surface was not washed) and Pelayo site (where street washing was performed daily during night). Following the chemical characterization of the road dust particles the emission sources were resolved by means of Positive Matrix Factorization, PMF (Multilinear Engine scripting) and the mass contribution of each source was calculated for the two sites. Mineral dust, brake wear, tire wear, carbonaceous emissions and construction dust were the main sources of road dust with mineral and construction dust being the major contributors to inhalable road dust load. To evaluate the effectiveness of street washing on the emission sources, the sources mass contributions between the two sites were compared. Although brake wear and tire wear had lower concentrations at the site where street washing was performed, these mass differences were not statistically significant and the temporal variation did not show the expected build-up after dust removal. It was concluded that the washing activities resulted merely in a road dust moistening, without effective removal and that mobilization of particles took place in a few hours between washing and sampling. The results also indicated that it is worth paying attention to the dust dispersed from the construction sites as they affect the emission strength in nearby streets. | H173: 11 | I173: 1 | J173: road dust emission sources and assessment of street washing effect
A174: 186 | B174: Optimization of Dengue Immunoassay by Label-Free Interferometric Optical Detection Method | C174: 2014-04-10 | D174: In this communication we report a direct immunoassay for detecting dengue virus by means of a label-free interferometric optical detection method. We also demonstrate how we can optimize this sensing response by adding a blocking step able to significantly enhance the optical sensing response. The blocking reagent used for this optimization is a dry milk diluted in phosphate buffered saline. The recognition curve of dengue virus over the proposed surface sensor demonstrates the capacity of this method to be applied in Point of Care technology. (Summary); Univ Politecn Madrid, Grp Micronano Photon & Biophoton, Ctr Laser, E-28040 Madrid, Spain. mariafe.laguna@upm.es; m.holgado@upm.es; fj.sanza@upm.es; alavin@etsii.upm.es; ana.lopez@upm.es; Rafael.casquel@upm.es (Author of contact); This work has been supported under the Project INNBIOD (REF: IPT-2011-1429-010000) under the Spanish Ministry of Economy and Competitiveness (INNPACTO program), the Project PLATON (REF: TEC2012-31145) under the Spanish Ministry of Economy and competitiveness (Plan Nacional 2012 Investigacion fundamental no orientada) and the project ENVIGUARD EUROPEAN PROJECT FP7-OCEAN-2013. We acknowledge specially Vircell S. L. for its technical and scientific support, as well as for offering the bio-chemical reagents to carry out this article. (Recognitions linked to item) | E174: Biosensors; Dengue virus; Label-free immunoassay; Photonic sensing cells | F174: Electrical and Electronic Engineering | G174: In this communication we report a direct immunoassay for detecting dengue virus by means of a label-free interferometric optical detection method. We also demonstrate how we can optimize this sensing response by adding a blocking step able to significantly enhance the optical sensing response. The blocking reagent used for this optimization is a dry milk diluted in phosphate buffered saline. The recognition curve of dengue virus over the proposed surface sensor demonstrates the capacity of this method to be applied in Point of Care technology. | H174: 3 | I174: 1 | J174: optimization of dengue immunoassay by labelfree interferometric optical detection method
A175: 187 | B175: On the improvement of annual performance of solar thermal power plants through exergy management | C175: 2014-04-01 | D175: Advancing in the learning curve of solar thermal power plants (STPP) requires detailed analysis for reducing exergy losses in the energy conversion chain. This requirement should be applied to any configuration proposed for the solar field and the power block. The aim of this work is to perform this type of analysis for two ways of structuring the power plant. The first plant structure consists of a subdivision of the solar collector field into specialized sectors with specific goals conveying different requirements in temperature. The second plant structure is based on a dual thermal energy storage system with a defined hierarchy in the storage temperature. The subdivision of the solar field into different sectors reduces the exergy losses in the heating process of the working fluid. Moreover, the average temperature of the heat transfer fluid in the solar field decreases when it is compared to the conventional solar field, reducing this way the exergy losses in the collectors. The dual thermal energy storage system is devised for keeping the exergy input to the power block at its nominal level for long periods of time, including post-sunset hours. One of the storage systems gathers a fluid heated up to temperatures above the nominal value and the second one is the classical one. The combination of both allows the manager of the plant to keep the nominal operation of the plant for longer periods than in the case of classical system. Numerical simulations performed with validated models are the basis of the exergy analyses. The configurations are compared to a reference STPP in order to evaluate their worth. Furthermore, the behaviour of the configurations is analysed to study the irreversibility of the included devices. Special attention is paid to the storage systems, as they are a key issue in both plant structures. Copyright (c) 2013 John Wiley & Sons, Ltd. (Summary); ETS Ingenieros Ind UNED, C Juan Rosal 12, Madrid 28040, Spain. rovira@ind.uned.es (Author of contact) | E175: Energy; Exergy analysis; Renewable energy; Solar thermal power plant; Systems; Thermal storage system | F175: Energy Engineering and Power Technology | G175: Advancing in the learning curve of solar thermal power plants (STPP) requires detailed analysis for reducing exergy losses in the energy conversion chain. This requirement should be applied to any configuration proposed for the solar field and the power block. The aim of this work is to perform this type of analysis for two ways of structuring the power plant. The first plant structure consists of a subdivision of the solar collector field into specialized sectors with specific goals conveying different requirements in temperature. The second plant structure is based on a dual thermal energy storage system with a defined hierarchy in the storage temperature. The subdivision of the solar field into different sectors reduces the exergy losses in the heating process of the working fluid. Moreover, the average temperature of the heat transfer fluid in the solar field decreases when it is compared to the conventional solar field, reducing this way the exergy losses in the collectors. The dual thermal energy storage system is devised for keeping the exergy input to the power block at its nominal level for long periods of time, including post-sunset hours. One of the storage systems gathers a fluid heated up to temperatures above the nominal value and the second one is the classical one. The combination of both allows the manager of the plant to keep the nominal operation of the plant for longer periods than in the case of classical system. Numerical simulations performed with validated models are the basis of the exergy analyses. The configurations are compared to a reference STPP in order to evaluate their worth. Furthermore, the behaviour of the configurations is analysed to study the irreversibility of the included devices. Special attention is paid to the storage systems, as they are a key issue in both plant structures. Copyright (c) 2013 John Wiley & Sons, Ltd. | H175: 7 | I175: 2 | J175: on the improvement of annual performance of solar thermal power plants through exergy management
